Workbook

Sheet README
A1: E4L Leads — daily batch
A2: Eat 4 Life Marketing · AI Marketing Made Easy · built by Claude, reviewed by humans
A4: What this is
A5: The review sheet for E4L's daily lead machine. Claude finds, qualifies, and researches 25 small-business leads per weekday and writes them here. Sam works the Sam Call Sheet tab (calls + follow-ups); Chosen reviews the Leads tab, approves, and loads approved rows into GoHighLevel (E4L Services sub-account). Nothing is emailed or called from this sheet itself.
A6: Daily batches arrive as dated sheets in the same Drive folder ('E4L Leads — YYYY-MM-DD'). This master file holds the playbook tabs, the suppression list, and the run log so the whole system is readable in one place.
A8: Sam: working the Call Sheet
A9: Open the Sam Call Sheet tab. Rows are sorted by Lead Score; every row has the best number, the owner's name and title, the timezone and best time to call, who answers the phone, a 20-second opener written for that business, the call angle, and the objection to expect.
A10: Cadence: Call 1 on the day the batch lands (use Best Time to Call). Call 2 two days later, leave a voicemail. Call 3 three days after that. Then the email bridge. 'Next Call Due' computes itself from what you log.
A11: Log every call the same day with the outcome dropdowns. Every call ends with ask #1 (Game Plan Call → log 'Game Plan Call booked' and the date) or ask #2 (email for the free GEO audit → log 'Email captured' and paste the address). 'Do not call' is permanent — those companies go on the Suppression tab.
A13: Chosen / Rozel: daily review in 5 steps (≈30 minutes for 25 rows)
A14: 1. Open the Leads tab (full research). Rows are sorted by Lead Score. Read Why Now, Attitude Type, Pain Signals, and the Personalized First Line.
A15: 2. Set Review Decision: Approve (load into GHL), Hold (good but not now), Reject (wrong fit — tell us why in Reviewer Notes so the rubric learns).
... A35: Green / amber / red score — Score band: 80–100 send today · 60–79 worth a touch · below 60 hold or reject.

Sheet Sam Call Sheet
A1: Lead ID | B1: Company | C1: Owner | D1: Title | E1: Best Number to Call | F1: Company Phone | G1: City | H1: ST | I1: TZ | J1: Best Time to Call | K1: Business Hours | L1: Gatekeeper Notes | M1: Score | N1: Attitude | O1: Entry Offer | P1: Call Opener (20 sec) | Q1: Call Angle | R1: Likely Objection | S1: Best Opening Moment | T1: After-Hours Handling | U1: Call 1 Date | V1: Call 1 Outcome | W1: Call 2 Date | X1: Call 2 Outcome | Y1: Call 3 Date | Z1: Call 3 Outcome | AA1: Next Call Due | AB1: Email Captured | AC1: Game Plan Call Date | AD1: Sam Notes | AE1: Website | AF1: Owner Email
A2: 20261012-01 | B2: Howard Injury Law | C2: Glen Howard | D2: Attorney | E2: Not found (a client review says Glen shared his personal cell, but no direct line is published; main line +1 702-331-5722, fax +1 702-629-7161 per site and NV Bar) | F2: +1 702-331-5722 | G2: Las Vegas | H2: NV | I2: America/Los_Angeles - Pacific Time (PDT, UTC-7 in October); Las Vegas, NV | J2: Tue-Thu 9:00-10:30 AM PT, right after the office opens at 9 and before Glen is on adjuster calls/court (he negotiates every bodily-injury case personally per the site FAQ schema); fallback Tue-Thu 4:00-4:45 PM PT before the 5 PM close. Avoid Mondays (post-weekend intake pile-up for a 3-person case team). The main line is CallRail-tracked and staffed by the case team during 9-5; ask for Glen by first name. | K2: Office: 'Monday to Friday, 9AM to 5PM PST' (site contact block, https://www.howardinjurylaw.com/contact-us/ and footer). Same page/header also says 'Free Consultation · Available 24/7' and JSON-LD Attorney schema claims openingHours 'Mo,Tu,We,Th,Fr,Sa,Su 24/7' (00:00-23:59). Spanish page: 'De lunes a viernes, de 9:00 a 17:00 (hora del Pacifico)' vs 'Consulta gratuita las 24 horas, los 7 dias de la semana'. GBP hours not opened directly. | L2: Main line +1 702-331-5722 is the office line (CallRail dynamic-swap tracked); no receptionist is named anywhere. Case team per About page (https://www.howardinjurylaw.com/about-us/): James Martin (15+ yrs legal field, role not stated; several Google reviews on the site name James, one calls him the case manager), Vanessa Kitchen (20+ yrs medical field, 10+ yrs practice administrator and marketing - most likely the office/ops lead and the best internal champion), Nathalie Sanabria (case manager). No answering service, call center or AI receptionist is credited; after hours the only named channel is the Intaker chat/text widget ('our 24/7 chat below'; YouTube bio '24/7 Help: intaker.com/howardinjurylaw/pi'). A Google review on the site says 'I had the lawyers personal cell number' - the cell is NOT published; do not ask for it. If the team answers: 'Hi, is Glen in? It's Sam - it's about the 24/7 line on the website.' If Vanessa answers, pitch her as champion (she ran a medical-practice front desk) and ask for 15 minutes with Glen. Careers page is 404; no job posts found (Indeed blocked), so no receptionist hire to reference. | M2: 71 | N2: Growth-Minded Operator (secondary: Tech-Forward Early Adopter) - confidence medium | O2: Free GEO audit (Chosen's matrix entry for PI law) paired with a bilingual (English/Spanish) AI voice-receptionist demo line built from howardinjurylaw.com; lead product on the Game Plan Call = AI voice receptionist with empathetic no-advice intake + missed-call text-back / speed-to-lead; GEO as the add-on. No prices in any asset. | P2: "Hi Glen, this is Sam with Eat 4 Life Marketing - this is a cold call, so feel free to hang up on me. I was on howardinjurylaw.com last night: the header says 'Free Case Review, 24/7, Talk with Glen,' and your contact page says Monday to Friday, 9 to 5. When a crash victim calls at 9pm, or calls in Spanish, who picks up right now - you, voicemail, or nobody? We build an AI receptionist trained on your own site that answers those calls, does a no-advice intake in English or Spanish, and books the consult - and we put a demo line on the phone you can call before you pay a dollar. Can I take 20 seconds to tell you how it works, or should I just send the demo number to ghoward@?" | Q2: Missed-call / after-hours bilingual intake is the wedge; the free GEO audit is the door-opener. Acknowledge he already pays for calls (CallRail tracking, Meta pixel, an ads agency) and that the site promises 24/7 in four languages with one attorney and three staff on a 9-to-5 office line. E4L's receptionist, trained on his own site, answers every missed or after-hours call, runs an empathetic intake (date of injury, treatment, insurer, no legal advice) in English or Spanish, books the consult, and texts back every missed call in under a minute - the caller never reaches the next firm on Google. Proof lever: a demo line built from howardinjurylaw.com he can call before paying anything. Respect his Intaker chat: it handles web chat/text, not the ringing phone. Never promise case volume or outcomes. | R2: 'We're already covered 24/7 - we have Intaker chat and texting, and clients can reach me on my cell.' Answer: chat and text catch the people who type; the voice agent catches the ones who dial at 9pm and get voicemail, and it drops them into the same intake - go-live is one conditional call-forwarding rule on missed/busy calls. Second objection: 'We already have an agency (Storm Media) doing SEO and GEO' - the audit is free, show the screenshots, do not bash the agency; pivot to the phone. Third (PI-specific): 'I get pitched by marketing guys every day' - lead with the demo number and one verifiable observation, not a pitch. | S2: The 24/7 promise on a one-attorney firm: homepage 'Free Case Review - 24/7 Talk with Glen!' and 'we're available 24/7 at (702) 331-5722' vs the contact block 'Monday to Friday, 9AM to 5PM PST' (https://www.howardinjurylaw.com/ and /contact-us/). Neutral, verifiable in 10 seconds, ties straight to the after-hours/bilingual intake gap. Secondary: his own 'we trained there' insurance-defense angle - he sells on knowing the other side's playbook, so frame E4L as showing him the caller's side of the phone. | T2: Site claims 'Available 24/7', 'Free Case Review - 24/7 Talk with Glen!' and 'Give us a call, we're available 24/7 at (702) 331-5722' while the contact block lists office hours 'Monday to Friday, 9AM to 5PM PST'. No answering service, call center or AI receptionist is named on the site, in page source, on BBB or on YouTube. The only named 24/7 channel is the Intaker chat/text widget ('fill out our simple form or our 24/7 chat below'; YouTube bio '24/7 Help: https://www.intaker.com/howardinjurylaw/pi') - chat/SMS, not phone. A client review on the site says 'I had the lawyers personal cell number', suggesting after-hours calls fall to Glen's own cell. GBP hours not opened directly. | AA2: =IF(A2="","",IF(OR(V2="Game Plan Call booked",V2="Do not call",V2="Not interested",V2="Email captured (GEO audit)",X2="Game Plan Call booked",X2="Do not call",X2="Not interested",X2="Email captured (GEO audit)",Y2<>""),"Done",IF(W2<>"",W2+3,IF(U2<>"",U2+2,"Call today")))) | AE2: https://www.howardinjurylaw.com | AF2: ghoward@howardinjurylaw.com
A3: 20261012-02 | B3: Viking Heating & Air Conditioning | C3: Nicole Bridge | D3: Owner / Member | E3: +1 480-689-5167 | F3: +1 480-689-5167 | G3: Chandler | H3: AZ | I3: AZ (Arizona, MST year-round, no DST; same clock as Los Angeles until Nov 1, 2026, then one hour ahead of LA) | J3: Tue-Thu 7:30-8:30 AM AZ (same as LA time until Nov 1): a one-office shop builds the day's dispatch board then, and with the dispatcher seat open the person on the main line is most likely Nikki (Member/Owner, registered agent, office side) rather than a hired gatekeeper. Second window Tue-Thu 4:00-5:30 PM AZ when Kelly (HVAC Tech/Owner) is back from the field. Avoid 9 AM-3 PM, when the line is fielding same-day no-cool calls during fall tune-up season, and avoid Mondays (weekend backlog) and Friday afternoons. | K3: No office hours published on viking-hvac.com, the careers page or BBB. Homepage and blog JSON-LD say open 00:00-23:59 Mon-Sun, and the Google Business Profile mirror (serviceagent.ai) shows 'Open 24 hours' every day with a 'Direct line - speak to a representative'; the site markets '24/7 emergency service' with 'emergency technicians always on call'. In practice it is a one-office shop whose dispatcher role is 'full-time, in-person' running a daily board, so treat the office as weekday daytime (roughly 7 AM-5 PM AZ) with the 24/7 line layered on top. | L3: Main line 480-689-5167 is the only number anywhere (site header, contact page, careers page, BBB, BuildZoom); CallRail is in the site code but the number matches every third-party record, so it is the real line, not a swapped tracking number. No office manager, receptionist, dispatcher or answering-service name is public, and the HVAC Dispatcher seat is currently open (full-time, in-person), so expect Nikki/Nicole Bridge or whoever is covering the board to pick up; no third-party answering service is mentioned anywhere. Kelly Bridge is 'HVAC Tech./Owner' and in the field - do not expect him midday. Ask for 'Nikki' (their own careers page uses that name; BBB has 'Nicole E. Bridge'). If a tech or fill-in answers: 'Is Nikki in the office this morning? It's about the dispatcher opening on your careers page' - true and specific. Their careers page brags 'Decisions made by people you actually know - Nikki and Kelly - not a call center in another state', so position the demo as backup for after hours and busy lines, never as replacing the dispatcher. No owner cell published; no 'no solicitation' notice seen. Second touch only: info@viking-hvac.com (generic, from their JSON-LD) addressed to Nikki or Kelly. Do not cite the Oct 2025 commercial-expansion press release (now 404); a tech named Logan Bridge appears in a recent review - do not assume a family relation. | M3: 69 | N3: Growth-Minded Operator | O3: Voice AI live demo built from viking-hvac.com (DEMO PATH, call-first to Sam with the demo number; email to info@ only as a gatekeeper-friendly second touch), framed on heating-season tune-up volume and the open dispatcher seat; add missed-call text-back. Do not lead with GEO - FAQ schema and an active blog already exist. | P3: Nikki? Sam with Eat 4 Life Marketing out of LA - and this is a cold call, so feel free to hang up on me. I was on Viking's careers page: you're hiring a dispatcher to run the daily board while the site promises 24/7 emergency service across 36 cities. We built a receptionist demo trained on viking-hvac.com that picks up the no-cool calls that ring while your dispatcher is on another line or after the office clears out, and books them. Can I take twenty seconds to tell you how it works, and you decide if it's worth a longer look? | Q3: Nikki, you're hiring a dispatcher at $21-25 an hour and telling 36 cities you're there 24/7. We built a receptionist demo from viking-hvac.com you can call right now: it picks up the calls that ring while your dispatcher is on another line or after hours, qualifies the no-cool emergency, and books it so nothing waits for the morning. Go-live is one call-forwarding rule for missed and busy calls, rollback is one dial code, and it can hand bookings to your existing Service Fusion setup. | R3: 'We run Service Fusion and we're hiring a dispatcher - we're covered.' Answer: keep both; this only takes the calls that would otherwise hit voicemail (busy, after hours, weekends) and hands the booking back to your dispatcher, so nothing changes for the team during the day - call the demo and judge it yourself before anything is bought. | S3: The live 'HVAC Dispatcher' post ($21-25/hr, 'running the daily dispatch board') paired with the careers line 'Decisions made by people you actually know - Nikki and Kelly - not a call center in another state' (https://blog.viking-hvac.com/careers, seen 2026-10-12): they are hiring for the phone seat and proud that calls stay local, which is exactly the after-hours gap the demo covers without replacing anyone. | T3: Unknown who answers after hours. Site claims: 'available 24/7' (repairs), 'we provide 24/7 emergency HVAC services throughout our entire service area' (FAQ), 'same-day service available for urgent situations'; homepage JSON-LD OpeningHoursSpecification Mon-Sun opens 00:00 closes 23:59; ServiceAgent mirror of GBP: 'Open 24 hours' every day (not verified on Google directly). No visible business hours on the site. No answering service, call center, or AI receptionist mentioned anywhere on site or in page source. Careers: 'not a call center in another state'; the dispatcher role is in-person and 'runs the daily dispatch board' (daytime). Gap = 24/7 promise with no stated after-hours answering mechanism. | AA3: =IF(A3="","",IF(OR(V3="Game Plan Call booked",V3="Do not call",V3="Not interested",V3="Email captured (GEO audit)",X3="Game Plan Call booked",X3="Do not call",X3="Not interested",X3="Email captured (GEO audit)",Y3<>""),"Done",IF(W3<>"",W3+3,IF(U3<>"",U3+2,"Call today")))) | AE3: https://www.viking-hvac.com/ | AF3: info@viking-hvac.com (generic office mailbox; present only in the company's JSON-LD page source on blog.viking-hvac.com and blog.viking-hvac.com/careers, not as visible text; no owner-personal email found on any public page)
A4: 20261012-03 | B4: Bob Heinmiller Air Conditioning, Inc. | C4: Mark Derringer | D4: Owner/President | E4: Not found (no owner cell or direct line on site, BBB, Carrier, or reviews; only the main line, fax, and the alternate 407-422-7657 office number) | F4: +1 407-374-0779 (site header 'Hotline', footer, BBB, DispatchCore). Also published: fax +1 407-422-0790; alternate +1 407-422-7657 (contact-page meta description 'Call Us Today' and Experience.com contact number); Carrier dealer page lists +1 321-319-3980 (different number on Carrier's locator - do not assume it reaches the office) | G4: Orlando | H4: FL | I4: America/New_York (Eastern) | J4: Tue-Thu 8:00-8:30 AM ET (Florida telemarketing floor is 8 AM; call before trucks roll and before the office queue builds - an Aug 11, 2026 public review says a morning caller was told 'she'd have to call me back this afternoon'). Fallback 4:00-5:00 PM ET when installs wrap. Ask for Mark Derringer (Owner/President) by name; if out, ask for Linda Heinmiller (Owner/Corp. Secretary). A 2023 review says the owner did not return four calls, so expect to book a time rather than get him live. | K4: Site publishes NO hours anywhere; only 'Same day and 24/7 emergency service available' and 'You can receive same-day care from a qualified expert 24 hours a day throughout the week' (https://www.bobheinmiller.com/). Google data mirrored by DispatchCore and YellowPages: 'Open 24 hours' Monday-Sunday (listing unclaimed). Sister entity Bob Heinmiller Solar Solutions (1519 W Smith St, same owners) lists Mon-Fri 8:00 AM-5:00 PM, closed Sat-Sun (Birdeye, TrustAnalytica). serviceagent.ai (Google data): 'After-hours and emergency response isn't signaled on the public profile.' | L4: Main line +1 407-374-0779 is answered by office staff, not the owner: Aug 11, 2026 review - 'I call for ac service this morning and the young lady said she'd have to call me back this afternoon' (https://www.solarreviews.com/installers/bob-heinmiller-solar-solutions,-llc.-reviews); a Jan 19, 2023 review on the solar entity names an office staffer 'Ashley' promising a callback 'within the hour' (STALE, role not stated). No office manager or dispatcher named on the site or in reviews; 'Meet Our Staff' lists only Bob Heinmiller (Founder), Linda Heinmiller (Owner/Corp. Secretary), Mark Derringer (Owner/President). Field names in reviews: techs Tyler, Chris; comfort advisor/sales Patrick Liner; installers Michael, Anthony. No answering service, call center, or AI receptionist vendor in page source. No owner cell published. Employment page lists 'Administrative' as an application category (no confirmed opening). Get through by asking for 'Mark Derringer' or 'Linda' by name and offering to book a 20-minute slot rather than pitching the person who answers. | M4: 69 | N4: Family-Legacy Pride Brand (primary); Growth-Minded Operator (secondary). Confidence: high (5+ signals across site, press, BBB, job boards). | O4: Voice AI live demo built from bobheinmiller.com (after-hours and overflow coverage on the hotline, booking into their process), framed as protecting a three-generation name - never as replacing office staff. Secondary ask: the free AI-visibility audit ('named in 0 of 3 so far; full 28-answer run on request'). Route: call-first (Sam) with the demo number; service@ email as backup with gatekeeper-friendly copy. demo_build = yes (D2 >= 9, site scrapable); run_geo_audit = yes (D4 = 6). | P4: "Hi, this is Sam with Eat 4 Life Marketing - this is a cold call, so feel free to hang up on me. I'm trying to reach Mark Derringer. The reason I'm calling: your homepage promises same-day, 24/7 service, but the '24/7 Call Service Support' button actually sends people to a web form, and one of your August reviews describes a morning caller being pushed to an afternoon callback. We build an AI receptionist trained on Bob Heinmiller's own site that picks up every call that rings out after hours or when the office is slammed, qualifies the caller, and books the visit - and you can call a demo line we build from your website before you pay anything. Can I take 20 seconds to tell you how it would work for a three-generation shop like yours, and you tell me if it's worth a longer conversation?" | Q4: Family-legacy protection + after-hours/overflow relief. Reference the 1945 roots and the July 2026 award, then the neutral observation that the homepage promises same-day/24-7 but the '24/7 Call Service Support' button lands on a web form and a recent public review describes a morning call deferred to an afternoon callback (summarize as a pattern; never quote the reviewer). Offer: a demo line trained on Bob Heinmiller's own site that answers what already rings out, qualifies the caller (name, number, address, no-cool vs. maintenance, urgency) and books the visit; go-live is one conditional call-forwarding rule, rollback is one dial code; nothing to pay before they hear it. Close with ask #1 (20-minute Game Plan Call with Sebastian) or ask #2 (an email address for the free AI-search audit - note they are not named for Orlando money questions in the checks run so far while AC's Heating & Air, Belle Air, and Aire Serv are). | R4: 'We already offer 24/7 service and our office handles the phones' / 'We've been here 36 years, referrals are our marketing' (Mark's own words: 'There is no better accolade or recognition than a business referral'). Answer: it only takes the calls that already ring out or get a 'we'll call you back' - referral callers still have to get through; the receptionist is trained on their story so callers still reach 'Bob Heinmiller'; office staff keep every call they answer; conditional forwarding only, no change to the number. Secondary objection: vendor fatigue / 'we have a marketing company' (Orange Rock Media builds the site; E4L is not a web or SEO replacement). | S4: The July 24, 2026 blog post 'Bob Heinmiller Solar Solutions named a 2026 Top Solar Contractor' (https://www.bobheinmiller.com/blog/) - a dated win within 90 days, safe to congratulate, and it pairs with the three-generation story. Then pivot to the neutral phone-process observation (site promises 24/7; the '24/7 Call Service Support' button goes to a web form). | T4: claims_24_7, coverage unverified. Site: 'Same day and 24/7 emergency service available' and '24/7 Call Service Support' (button links to /contact-us/ web form, not a phone line). Google data via unclaimed mirrors: 'Open 24 hours' Mon-Sun. No answering-service, call-center, or AI-receptionist vendor in page source. Sister solar entity lists Mon-Fri 8-5 only. Aug 11, 2026 review shows daytime calls being deferred to callbacks. Sam should record who answers on the first dial. | AA4: =IF(A4="","",IF(OR(V4="Game Plan Call booked",V4="Do not call",V4="Not interested",V4="Email captured (GEO audit)",X4="Game Plan Call booked",X4="Do not call",X4="Not interested",X4="Email captured (GEO audit)",Y4<>""),"Done",IF(W4<>"",W4+3,IF(U4<>"",U4+2,"Call today")))) | AE4: https://www.bobheinmiller.com | AF4: Not found
A5: 20261012-04 | B5: Appalachian Tree Service of Atlanta, Inc. | C5: Ryan Strache | D5: President/Owner | E5: Not found (only the main line +1 404-409-9926 is published on site, BBB and Nextdoor; line type not stated, do not text) | F5: +1 404-409-9926 | G5: Kennesaw | H5: GA | I5: America/New_York (Eastern Time) | J5: Tue–Thu 4:15–5:00 PM ET — the last 45 minutes of his posted Mon–Fri 9–5 window, when a climber-led crew is off the tree and the site says requests are reviewed 'during our stated operating hours'; fallback Mon–Fri 9:00–9:30 AM ET right at opening before the crew rolls. Do not call outside 9–5 ET (closed; voicemail only). | K5: Mon–Fri 9:00 AM–5:00 PM; Sat–Sun Closed for normal operations (contact page, JSON-LD OpeningHoursSpecification, Nextdoor). EXCEPTION on the 48 /storm-damage/{city} pages: 'Weekend calls are accepted for urgent storm inquiries and estimates. No after-hours nighttime dispatch.' Google Business Profile not opened directly. | L5: No office manager, dispatcher or answering service is named anywhere (site, BBB, Nextdoor; no vendor scripts in source). The only mailbox is ryan@, and a Nextdoor reviewer refers to 'Ryan and his staff', so the main line +1 404-409-9926 most likely rings to Ryan or straight to voicemail during a job. Ask for Ryan by first name; if a crew member answers, ask when Ryan reviews estimate requests (site says during 9–5) and call back then. Line type not published — manual dial only, no SMS. If voicemail: leave name, 'built a demo line for Appalachian Tree Service', and let Sebastian's email carry it. | M5: 68 | N5: Growth-Minded Operator (medium confidence: 4 signals across 2 source categories - website + third-party profiles); secondary: Overwhelmed Owner-Operator | O5: Voice AI live demo built from appalachiantreeservice.com (generic home-services template: trade = tree service; scenario = tree down on the house after a storm at 9 PM; the AI qualifies the caller, captures address/damage details and books the first-morning assessment - no nighttime dispatch promised) + missed-call text-back. demo_build = yes (phone-first, D2 = 15, site scrapes cleanly). run_geo_audit = after D4 spot-check. | P5: Hi Ryan, this is Sam with Eat 4 Life Marketing — this is a cold call, so feel free to hang up on me. I was on your site this week: nice October hazard-tree special. I also noticed your storm-damage pages say there's no after-hours nighttime dispatch — which makes sense when you're the one in the tree. We build an AI receptionist trained on your own company that picks up the 9 PM storm call, gets the address and what came down, and books your first morning assessment — and we build the demo line from your website before you pay anything. Can I take 20 seconds to tell you how it works, or is this a bad time? | Q5: Relief + coverage, not growth: he is the climber, the estimator and the inbox, and he is paying to drive calls right now (October 10%-off hazard-tree promo, brand-new site, 48 storm-damage city pages added Sept 1) while evening calls go to voicemail. Pitch the storm-week scenario: an AI receptionist trained on his own site answers the after-hours and overflow calls, qualifies the caller (name, address, what fell, photos via the form link), and books the morning assessment — it never dispatches at night, it just keeps the lead. Proof lever: 'we already built a demo line from your website; call it before you pay a dollar.' Go-live = one conditional call-forwarding rule for missed/busy calls; rollback is one dial code. Ask #1: 20-minute Game Plan Call. Ask #2: the free AI visibility check once D4 runs. Keep it to 3 short lines; do not say he misses calls (reviews praise his response speed) and do NOT say weekends are uncovered (his storm pages accept weekend urgent calls) — say 'after 5 PM' / 'overnight'. | R5: 'I'm a small climber-led crew and I don't do night work — I don't need more calls I can't handle.' Answer: the receptionist does not dispatch anything; it answers, captures the details and books the assessment into the next open morning so you choose the jobs instead of losing them to whoever picked up. Secondary: 'I just rebuilt the site / I handle the phone myself' — it only covers the calls that already go to voicemail, trained on that new site, nothing for you to set up beyond one forwarding rule. Budget sensitivity is likely (solo email, no office staff) — keep pricing for the Game Plan Call. | S5: The live October promotion: 'October Special • Active Oct 1 – Oct 31 — Don't Let Spooky Trees Haunt Your Home — Save 10% This October' on the newly relaunched site (https://www.appalachiantreeservice.com/, seen 2026-10-13). Dated, positive, business-specific and his own words; pairs naturally with 'every call that promo brings in after 5 PM currently waits until morning' (contact page: 'We review requests during our stated operating hours'). | T5: No nighttime coverage claimed. Homepage Service JSON-LD: 'Storm-damage inquiries, assessment and cleanup ... during listed inquiry hours; no nighttime dispatch'. /storm-damage/kennesaw (and 47 sibling city pages, 2026-09-01): 'Storm inquiry hours Monday–Friday: 9:00 AM–5:00 PM for normal operations and dispatch. Saturday–Sunday: Weekend calls accepted for urgent storm inquiries and estimates. There is no after-hours nighttime dispatch.' Contact page: 'We review requests during our stated operating hours.' No 24/7 claim, answering service, AI receptionist or IVR vendor in page source. Gap to pitch = evenings/nights (after 5 PM), NOT weekends. | AA5: =IF(A5="","",IF(OR(V5="Game Plan Call booked",V5="Do not call",V5="Not interested",V5="Email captured (GEO audit)",X5="Game Plan Call booked",X5="Do not call",X5="Not interested",X5="Email captured (GEO audit)",Y5<>""),"Done",IF(W5<>"",W5+3,IF(U5<>"",U5+2,"Call today")))) | AE5: https://www.appalachiantreeservice.com | AF5: ryan@appalachiantreeservice.com
A6: 20261012-05 | B6: Blue Peaks Roofing LLC | C6: Andrew Ubben | D6: Owner | E6: +1 303-808-0687 | F6: +1 303-808-0687 | G6: Littleton | H6: CO | I6: MT | J6: Tue-Thu 8:00-8:45 AM MT, right at office open, before project consultants and crews head out to roofs (hours are 8-5 weekdays and the site funnel is callback-based, so the 303 line is most likely picked up by a live person first thing); fallback Tue-Thu 4:00-4:50 PM MT before the 5 PM close. Avoid Mondays (storm-claim backlog) and anything after 5 PM or weekends, which go to voicemail per the published hours. | K6: Mon-Fri 8:00 AM-5:00 PM, Sat-Sun closed (Parker Chamber member listing 'Mon-Fri - 8am - 5pm'; leadstal GBP mirror shows the same). Site itself lists no hours; it says emergency repairs are handled 'during normal business hours' and 'We call you back to set a time.' | L6: No office manager, dispatcher or receptionist is named anywhere (site, reviews, BBB, chamber, LinkedIn). The only number on the site, BBB, JSON-LD and PRs is (303) 808-0687; no answering service, call tracking or AI receptionist detected, and the site says 'We call you back to set a time,' so expect either whoever is at the desk 8-5 MT or voicemail. Ask for 'Andrew' (Andrew J. Ubben, BBB principal/Owner); if they say the owner is 'Mike' (Mike McCoy, named Owner in 2026 paid press releases), take the hand-off and confirm on the call who owns phones/marketing — do not insist on either name. Public side door: Alyssa McGuinnis, Project Consultant, cell (303) 882-2061 (Parker Chamber rep listing) — sales-side, useful to ask 'who handles the phones and marketing' but not to pitch as owner. Project-side staff named in reviews/LinkedIn (Benny Izquierdo, Grant, John Y., Michael G., Kaleb, Diego Martinez) — if one answers, they are on jobs, keep it to 'who handles after-hours calls and marketing?' and get a callback window. Mirror their line 'the claim stays yours — we never file claims for homeowners'; no claim-handling promises. Do not use (970) 410-3778 or (720) 202-1127 (stale). Do not repeat their unverified Team Dave Logan / Quality Business Awards claims. | M6: 66 | N6: Growth-Minded Operator (secondary: Tech-Forward Early Adopter) — confidence medium | O6: Voice AI live demo line built from bluepeaksroofing.com — after-hours/overflow receptionist that qualifies the caller (address, leak vs. hail, claim status) and books the free inspection — paired with missed-call text-back; Revenue Leak Scorecard as the email CTA (no links until warm-up clears); GEO audit as a later touch once the AI spot-check is run. | P6: Hi, this is Sam with Eat 4 Life Marketing — is this Andrew? Full disclosure, this is a cold call, so you're welcome to hang up on me. I saw Blue Peaks' LinkedIn post this week — a roof replacement shouldn't feel like 'radio silence until a dumpster shows up.' I also noticed your site says emergency repairs are business-hours only, and the Littleton homeowner who calls at 7 PM after a hailstorm is dialing the next roofer on Google. We built a demo receptionist from bluepeaksroofing.com that answers after-hours and overflow calls, asks the leak-or-hail and claim questions your consultants ask, and books the free inspection — you can call it and hear it before anyone talks money. Can I take 20 seconds to tell you how it works, and you tell me if it's worth a longer look? | Q6: Your site says emergency repairs happen during normal business hours and that you call people back to set a time — in hail season that callback window is exactly when a homeowner dials the next roofer who picks up. We built a demo receptionist from bluepeaksroofing.com that answers after hours and overflow calls, asks the leak-or-hail and insurance questions your consultants ask, and books the free inspection; you can call it and hear it before anyone talks money. Go-live is one conditional call-forwarding rule on missed calls and rollback is one dial code, so nothing about how your team works changes. | R6: "We already answer everything — communication is our whole brand, and we have a system (GHL form / marketing vendor)." Answer: keep all of it — this only catches the calls that already ring out after 5pm or while your consultants are on roofs, and books them into whatever you use today; hear the demo first and decide after. | S6: LinkedIn company post ~Oct 10, 2026 (shown as "2d" ago on Oct 12): "A roof replacement shouldn't feel like radio silence until a dumpster shows up." — their own words about communication, 2 days old, safe and positive; URL https://www.linkedin.com/company/blue-peaks-roofing-littleton-co. Backup: July 23, 2026 hail-season inspection expansion release. | T6: Unknown — nothing published. Site home + FAQ: "We make emergency repairs during normal business hours." / FAQ: "Yes. We handle emergency repairs during normal business hours." Contact page: "Emergency repairs are available during business hours." and "We call you back to set a time." No hours listed on the site; no 24/7 claim; no answering service, call center, text-back, or AI receptionist mentioned anywhere in page source. Aggregator-shown GBP hours (unverified): Mon-Fri 8 AM-5 PM, Sat-Sun Closed (https://www.leadstal.com/sb/blue-peaks-roofing). | AA6: =IF(A6="","",IF(OR(V6="Game Plan Call booked",V6="Do not call",V6="Not interested",V6="Email captured (GEO audit)",X6="Game Plan Call booked",X6="Do not call",X6="Not interested",X6="Email captured (GEO audit)",Y6<>""),"Done",IF(W6<>"",W6+3,IF(U6<>"",U6+2,"Call today")))) | AE6: https://bluepeaksroofing.com | AF6: admin@bluepeaksroofing.com
A7: 20261012-06 | B7: Shockley Electric LLC | C7: Christian Shockley | D7: Not found | E7: Not found (only the main line +1 770-630-6858 is published; with a 2-person crew it may be his cell — manual dial only) | F7: +1 770-630-6858 (main line; same number on site tel: links, BBB, Nextdoor, Thumbtack — CONFIRMED. 2-person shop, so this may ring to the owner's cell: manual human dial only, no SMS/AI outbound.) | G7: Marietta | H7: GA | I7: ET | J7: Tue-Thu 8:00-8:50 AM ET, just before the posted 9:00 open and before he is on a ladder; fallback Tue-Thu 4:30-5:30 PM ET as jobs wrap and before the line 'closes' at 5:30. Reason: Thumbtack shows '2 employees' and reviews describe Christian personally doing 4-hour jobs, so mid-day (9:30-4:00) the only published number is in a panel and rings to voicemail. Skip Mondays (solo scheduler's catch-up day) and weekends (Closed). | K7: Mon-Fri 9:00 AM-5:30 PM, Sat-Sun Closed (Nextdoor listing). Thumbtack shows Mon-Fri 9:00 AM-5:00 PM, Sat/Sun Closed. Website lists no hours and no 24/7 claim; Google Business Profile not accessible this session. | L7: No gatekeeper. Two-employee shop (Thumbtack: 'Hired 60 times, 2 employees, 12 years in business'); no office manager, dispatcher, answering service or AI receptionist found on the site, BBB, Nextdoor or Thumbtack, and the single published number 770-630-6858 appears on every page - almost certainly Christian's own cell, so expect him or voicemail. Reviews name only Christian as the person doing the work. A second person replies for the business on Nextdoor (initials 'T. J.', Hiram, GA) - possibly the second employee; if someone else answers, ask for Christian by first name ('Is Christian around? It's Sam'). Ignore the contact-page fax +1 800 889 9898 (placeholder). On voicemail leave a 10-second message naming the demo line, no pitch, and log 'who answered' on first dial. Manual human dial only - no SMS or AI outbound to this number since it may be a personal cell. Tone: terse, anti-upsell ('we do not upsell') - no hype, no 'AI' lead-in, do not quote a Google review count. | M7: 66 | N7: Overwhelmed Owner-Operator (primary, medium confidence); Marketing-Burned Skeptic (secondary) | O7: Voice AI live demo built from shockleyelectric.com (safety-triage branch for sparking/burning-smell calls, panel-upgrade quote capture, books the free estimate) + missed-call text-back. Add the free GEO audit as the second touch once the spot-check is run (no schema on site). | P7: "Christian? Sam with Eat 4 Life Marketing - straight up, this is a cold call, you can hang up on me. Your site says 'call us now to schedule,' and Nextdoor shows the line closing at 5:30 and on weekends. With a two-man crew I'd bet some panel-upgrade calls hit voicemail while you're in a box - and that homeowner just calls the next electrician on Google. We built a demo receptionist from shockleyelectric.com you can call before you pay a dollar - it picks up when you can't, asks if something's sparking, and books the free estimate. Got 20 seconds for me to explain, then you tell me if it's worth a longer look?" | Q7: "Christian, it's Sam with Eat 4 Life Marketing. We built a demo receptionist from shockleyelectric.com you can call right now — it picks up when you're on a ladder or it's after 5:30, asks whether something's sparking or smells hot, and books the free estimate for a panel upgrade. Nothing to buy to hear it; if you don't like it, hang up on it." Qualify: "Who picks up right now when you're mid-job — you, voicemail, or nobody?" | R7: "I answer my own phone — it's just me and one guy, I don't need a receptionist." Answer: "Keep answering. This only catches the calls that already hit voicemail — after 5:30, weekends, when you're in a panel — and books them; go-live is one call-forwarding rule and rollback is one dial code." | S7: The Nextdoor 'Our story' line 'The Electrician Marietta GA Calls First' paired with the posted hours (Mon–Fri 9–5:30, closed weekends) — a neutral, verifiable observation about his phone process that leads straight to the demo (https://nextdoor.com/pages/shockley-electric-marietta-ga/). Backup compliment: Expertise.com 'Best Electricians in Roswell, GA 2026' list updated Oct 8, 2026 (https://www.expertise.com/ga/roswell/electricians); safest brag to mirror: lifetime labor guarantee and 'we do not upsell'. | T7: Unknown / not stated. Hours: Mon–Fri 9:00 AM–5:30 PM, Sat–Sun Closed (Nextdoor; Thumbtack confirms Sun Closed). Site mentions 'emergency repairs' but makes no 24/7 claim, lists no after-hours number, answering service, or AI receptionist, and page source has no answering/AI vendor scripts. With a 2-person crew and phone-only scheduling, after-hours and on-the-job calls most likely reach voicemail (not verified — Sam records 'who answered' on first dial). | AA7: =IF(A7="","",IF(OR(V7="Game Plan Call booked",V7="Do not call",V7="Not interested",V7="Email captured (GEO audit)",X7="Game Plan Call booked",X7="Do not call",X7="Not interested",X7="Email captured (GEO audit)",Y7<>""),"Done",IF(W7<>"",W7+3,IF(U7<>"",U7+2,"Call today")))) | AE7: https://shockleyelectric.com/ | AF7: christian@shockleyelectric.com
A8: 20261012-07 | B8: Light It Up Electric, Inc. | C8: Todd Guernsey | D8: Owner / Texas Master Electrician | E8: Not found (only the main line 469-261-1503 appears on the site, BBB, JSON-LD and the TDLR record) | F8: +1 469-261-1503 (site header/footer tel: link, JSON-LD, BBB, TDLR license record all match) | G8: Frisco | H8: TX | I8: America/Chicago (Central Time) | J8: Tue–Thu 8:05–8:45 AM CT, with 4:00–4:45 PM CT as the fallback. Reason: the site posts 'Reception Hours' starting at 8:00 (contact page/footer) or 9:00 (appointment page), so a staffed office line opens then and crews are least likely to be mid-job early; after 5:00 PM and weekends the line is closed, so never call then. Nothing public says the owner answers the main line, so expect reception and ask for Todd by name. | K8: Mon–Fri 8:00 AM–5:00 PM, Sat–Sun Closed (site footer, FAQ 'We are open Monday through Friday 8:00 am to 5:00 pm', and OpeningHoursSpecification JSON-LD). 'Reception Hours' shown as Mon–Fri 9:00 am–5:00 pm on /schedule-an-appointment but 8:00 am–5:00 pm on /contact — minor conflict. No 24/7 or emergency hours anywhere; live GBP hours not fetched. | L8: The site posts "Reception Hours," so expect a receptionist/office person on 469-261-1503 during 8–5 CT (name not published; BBB lists no customer contact). Natasha Guernsey is named on the company site as the author of every blog post (role not stated) and is the likely office/marketing contact and a possible champion — if she answers, reference the Halloween panel posts. Ask for "Todd Guernsey, the master electrician" by name; no owner cell or direct line is published anywhere public. If routed to email, Info@LightItUpElectric.net is on Google Workspace (good deliverability); LightItUpElect@aol.com is the address the appointment page shows under "Email us." Do not mention family relationships; treat Natasha only as a named company contact. | M8: 66 | N8: Unclear (leans Growth-Minded Operator; Family-Legacy Pride Brand secondary) | O8: Voice AI live demo — an after-hours/overflow receptionist trained on lightitupelectric.net that answers the calls reception misses after 5 PM and on weekends, triages 'sparking/burning smell' urgency, books the estimate, and can mention the Advantage Plan; pair with missed-call text-back and sub-60-second form reply. Ask #2: free AI visibility audit for 'EV charger installer / electrician near Frisco, TX'. | P8: Hi Todd — Sam with Eat 4 Life Marketing. Full disclosure, this is a cold call, so feel free to hang up on me. I was on lightitupelectric.net and the Advantage EV+ plan caught my eye. Here's why I'm calling: your site says "if you need us right now, call us," but reception closes at 5 and all weekend, so a 7 PM panel or EV-charger call hits voicemail and that homeowner calls the next electrician on Google. We built a receptionist trained on your own website that picks those up and books the estimate — you can call it before you pay a dollar. Can I take 20 seconds to explain how it works, and you tell me if it's worth a longer look? | Q8: Coverage gap, not growth: the site tells people "if you need us right now, call us" and promises same-day response, but reception closes at 5 and all weekend, so a warm-outlet, tripped-panel or EV-charger call at 7 PM hits voicemail and that homeowner dials the next electrician — the exact "shop around" problem their own memberships page says they lose to. Proof-first: E4L builds a demo line trained on their own site they can call before paying; go-live is one conditional call-forwarding rule for missed/busy calls, rollback is one dial code, and a human still answers everything they already pick up. Secondary: every after-hours caller the receptionist books is a natural Advantage Plan prospect. | R8: "We're a small family shop and reception already handles the phones — we get back to everyone the same day." Answer: it only touches calls that already go to voicemail (after 5, weekends, line busy); nothing changes about who answers during the day; hear the demo first, no commitment. Expect pragmatic skepticism of marketing vendors (niche read: allergic to hype, will try to break the demo) — lead with the demo number, not features, and never say "AI" first. | S8: The Advantage EV+ membership plan plus the twice-weekly Halloween-themed blog run (Oct 6 'No Tricks — Just a Safer Home', Oct 8 'Frankenstein Says: Check the Panel!'), both dated within the last 7 days on https://www.lightitupelectric.net/blog and /memberships — recent, specific, positive, and about their business. Fallback: 'Voted Best Electrician in Frisco' banner (undated) and 26 years family-owned. | T8: hours_only. Site/JSON-LD: Mon–Fri 08:00–17:00, 'Saturday to Sunday : Closed'; no 24/7, emergency-line, answering-service, call-center or AI-receptionist text anywhere in the fetched source of /, /contact, /schedule-an-appointment, /faqs, /memberships. Yet the site promises 'Same-Day Response' (memberships page), 'Will Get Back To You The Same Day' (home), 'If you need us right now call us at 469-261-1503' (form confirmation), and the FAQ tells warm-outlet callers to 'call us immediately'. After 5 PM and all weekend the only path is voicemail or a form answered 'as soon as possible'. | AA8: =IF(A8="","",IF(OR(V8="Game Plan Call booked",V8="Do not call",V8="Not interested",V8="Email captured (GEO audit)",X8="Game Plan Call booked",X8="Do not call",X8="Not interested",X8="Email captured (GEO audit)",Y8<>""),"Done",IF(W8<>"",W8+3,IF(U8<>"",U8+2,"Call today")))) | AE8: https://www.lightitupelectric.net | AF8: Info@LightItUpElectric.net
A9: 20261012-08 | B9: By The Book Plumbing LLC | C9: James Smith | D9: Owner / Co-founder | E9: Not found (only the main line 281-907-2092 is published; the TSBPE RMP record lists no phone) | F9: +1 281-907-2092 | G9: Spring | H9: TX | I9: CT | J9: Tue-Thu 7:30-8:00 AM CT, before his first job (listed hours start at 8 AM), with a backup window 4:00-5:00 PM CT right after listed hours end. Reason: no office staff, dispatcher or answering service appears in any public source; reviews show James schedules and does the work himself ('James offered the first available appointment'; review replies signed '-James'), so midday he is under a water heater and the published line likely rings to him. Avoid Monday mornings (weekend backlog) and Friday after 2 PM. | K9: Mon-Fri 8:00 AM-4:00 PM; Sat-Sun Closed (Google Business Profile mirror via LeadsTal and the Nextdoor business page agree). The site's Spring TX page claims 'round-the-clock' emergency response and Yelp reportedly lists 'open 24 hours', but (281) 907-2092 is the only published line and no after-hours coverage is named. | L9: No gatekeeper found. No office manager, dispatcher, receptionist or answering service is named on the site, Nextdoor, Trustindex (727 reviews), the GBP mirror, conroedirect or the 2018 Voyage Houston interview; the TSBPE record lists no phone. The only published number, (281) 907-2092, appears to ring to James himself (he schedules jobs personally per reviews and signs replies '-James'), and it may be his cell, so human dial only, no SMS or AI voice to that line. Dana Smith is named co-founder on the homepage (the 2018 interview mentions his wife without a role); if she answers, ask for James by name and say it is about the Saturday and after-4 PM calls. If voicemail: leave a 10-second message naming the demo line, then email james@bythebookplumbing.com (printed in the site footer). Neighbors call him 'old school' and code-driven, so do not open with 'AI'; stress it is trained on his site and answers as By The Book. | M9: 65 | N9: Overwhelmed Owner-Operator (medium confidence; secondary Family-Legacy Pride cues) | O9: Voice AI live demo built from bythebookplumbing.com with the emergency/after-hours angle, paired with missed-call text-back (door-opener = demo number; D2 = 15 and the site is scrapable, but throttle the scraper - the site WAF began returning 403 after roughly 15 rapid fetches). Run the GEO audit before send since D4 is unchecked. | P9: James? Sam with Eat 4 Life Marketing. This is a cold call, so I'll be quick. Your Google listing closes at four and shows weekends off, but your Spring page promises round-the-clock emergency service, so I'm guessing a Saturday water-heater leak hits voicemail while you're under a tank, and that homeowner calls the next name on Google. We build a receptionist trained on your own site that answers as By The Book, books the job, and texts back every missed call in under a minute. You can call it and hear it before you pay a dollar. Can I take twenty seconds to tell you how the demo line works, and if it's not for you, I'll let you go? | Q9: James, your Google listing says you offer emergency plumbing, but hours stop at 4 and weekends show closed, so a Saturday-night water-heater leak in Spring probably lands in voicemail and that homeowner calls the next plumber on Google. We built a receptionist from your own website that picks up those calls, gets the name, address and what's leaking, books it or texts them back in under a minute, and you can hear it answer as By The Book before you pay anything. Going live is one call-forwarding rule for missed calls, and one dial code turns it off. | R9: "It's just me, I'm already booked a week out, and I don't want a robot talking to my customers." Answer: it only takes the calls you already can't (missed, after 4pm, weekends), introduces itself as By The Book's assistant, captures the water-heater and tankless jobs you want and politely refers the rest, so the schedule fills with the right work instead of callers going to the next plumber; hear it on the demo line first, nothing to buy until you have. | S9: 671 Google reviews at 5.0 that name James personally (Trustindex) set against the GBP listing that says "Yes, we offer emergency plumbing services" while hours read Mon-Fri 8 AM-4 PM, Sat/Sun Closed (LeadsTal GBP mirror) - a neutral, verifiable observation about who picks up the phone. Backup: Nextdoor neighbors calling him "old school" and "a hidden gem". | T9: Unknown / no coverage stated. GBP mirror (LeadsTal) and the Nextdoor business page both list Mon-Fri 8 AM-4 PM, Sat/Sun Closed. The site's Spring TX landing page (https://bythebookplumbing.com/spring-texas/) DOES claim 'Plumbing problems don't adhere to regular business hours, and neither do we… providing round-the-clock services when you need them' (home/about/contact pages make no 24/7 claim). No answering service, office line, dispatcher or after-hours number is published anywhere. Yelp reportedly lists 'open 24 hours' (page could not be opened). Who picks up after 4 PM or on weekends is not stated. | AA9: =IF(A9="","",IF(OR(V9="Game Plan Call booked",V9="Do not call",V9="Not interested",V9="Email captured (GEO audit)",X9="Game Plan Call booked",X9="Do not call",X9="Not interested",X9="Email captured (GEO audit)",Y9<>""),"Done",IF(W9<>"",W9+3,IF(U9<>"",U9+2,"Call today")))) | AE9: https://bythebookplumbing.com/ | AF9: james@bythebookplumbing.com
A10: 20261012-09 | B10: ScissorTail Roofing & Construction | C10: Matt Morgan | D10: Owner | E10: +1 405-452-0591 — LIKELY, not confirmed as owner-direct: listed as "Contact phone" under "Contact name Matt Morgan" in the May 5, 2025 GetFeatured press placement media-contact block; scout noted an older directory shows it as the Norman office line; not labeled cell/direct anywhere. Manual human dial only; line type unknown. | F10: +1 405-928-8089 (site header/footer tel link, Contact page, BBB — CONFIRMED main line) | G10: Norman | H10: OK | I10: America/Chicago — Central Time (CDT in October, UTC-5) | J10: Tue–Thu 8:00–8:45 AM CT, right at office open before account managers and production staff head to job sites (office line staffed from 8:00 per site hours; trades window per playbook); fallback Tue–Thu 4:30–5:45 PM CT before the 6:00 PM close when field staff are back. Avoid Mondays (storm-week callback backlog) and anything outside 8–6 (site says after-hours is emergencies only). | K10: Mon–Fri 8:00 AM–6:00 PM; Saturday and Sunday "By Appointment"; "24/7 Emergency Services Available" / "around the clock for emergencies" (site homepage, Contact page, JSON-LD openingHoursSpecification Mon–Fri 08:00–18:00). Google Business Profile hours not readable this run. | L10: Who answers the main line (405) 928-8089 is not published — no office manager/dispatcher named on site, BBB, or reviews (reviews not readable). Published contact is Matt Seaton, Director of Operations (matt.seaton@scissortailroofing.com; "regularly find him in the field talking with our customers"). Account-management team that likely fields inbound: Lance Uhles (Director), Nich Lanier and Mitchell Smith (Account Managers). The estimate widget says messages go to "his personal phone" — unnamed. Two Matts: ask for "Matt Seaton" first (he is the published contact and runs operations/efficiency programs — natural champion), then "Matt Morgan, the owner". Second line (405) 452-0591 is tied to Matt Morgan as media contact in the May 2025 press release — try it only as a manual dial if the main line stalls. No answering service or IVR detected. | M10: 65 | N10: Growth-Minded Operator (secondary: Tech-Forward Early Adopter) — medium confidence | O10: Voice AI live demo line built from scissortailroofing.com — positioned as after-hours/overflow coverage behind their own "Responses within 2 hrs" promise: answers the 24/7 emergency line when the personal phone is on a roof, qualifies storm/leak urgency, captures address + insurance status, books the free estimate; pair with missed-call text-back on the SMS-consented estimate form. GEO audit only as a secondary touch (site already schema-ready). demo_build = yes (D2 = 15, site scrapable, 38 clean pages). | P10: "Hi, this is Sam with Eat 4 Life Marketing — this is a cold call, so feel free to hang up on me. I was on scissortailroofing.com and saw you promise 24/7 emergency service across Central Oklahoma while the office runs eight to six, and estimate requests go straight to somebody's personal phone. We built a demo receptionist for ScissorTail from your own site — it only picks up the calls that ring out after six or during a hail week, qualifies the caller, and books the free estimate. Can I take twenty seconds to tell you how it works, and you tell me whether it's worth hearing?" | Q10: Missed-call / after-hours voice demo. Matt Morgan spent 15 years in software management and the company already runs a GEO-ready site, so skip "AI education" and GEO; lead with proof: a demo receptionist already built from their own site that only takes the calls that ring out after 6pm, on weekends ("By Appointment"), and during hail-week surges across 9 cities — then books the free estimate and texts the caller back. Frame it as protecting the "Responses within 2 hrs" promise and the Google Guaranteed leads they are already paying for, not replacing Matt Seaton's team. Secondary champion: Matt Seaton (Director of Operations, "operation and efficiency programs") — the demo is something he can forward to the three owners. | R10: "It goes straight to my personal phone and we respond within two hours — we don't miss calls." Response: agree, and point out the demo only picks up when that phone can't (on a roof, after 6, Sunday storm night); offer to let them call the demo line and hear it; go-live is one conditional call-forward rule on missed/busy calls, rollback is one dial code. Second objection: "we already have a new website / we're Google Guaranteed" — reply that this is about the calls those investments generate, not more marketing. | S10: Matt Morgan serving as Board President of the Oklahoma Roofing Contractors Association (site About; undated) — safe, professional compliment. Operational hook: the site promises "24/7 Emergency Services Available" / "Responses within 2 hrs" while hours are Mon–Fri 8–6 and estimate texts go "straight to my personal phone" (homepage). Secondary: new website built ~May 2026 (robots.txt "Generated: May 2026", Astro v6.2.1, © 2026). | T10: claims_24_7 with hours_only staffing — Site: "24/7 Emergency Services Available" (homepage badge), FAQ: "Yes, we provide 24/7 emergency roofing services for storm damage and urgent repairs across Central Oklahoma", Norman page: "Emergency response available 24/7"; Contact page: "We are available Monday through Friday from 8a to 6p, by appointment outside those hours, and around the clock for emergencies"; hours block "Mon–Fri 8:00 AM - 6:00 PM · Sat By Appointment · Sun By Appointment"; header promise "Responses within 2 hrs". Estimate widget: "Replies on his personal phone — This text goes straight to my personal phone." No answering service, IVR, call center, or AI receptionist mentioned anywhere on site or in page source. Who actually answers after 6pm: Not found. | AA10: =IF(A10="","",IF(OR(V10="Game Plan Call booked",V10="Do not call",V10="Not interested",V10="Email captured (GEO audit)",X10="Game Plan Call booked",X10="Do not call",X10="Not interested",X10="Email captured (GEO audit)",Y10<>""),"Done",IF(W10<>"",W10+3,IF(U10<>"",U10+2,"Call today")))) | AE10: https://www.scissortailroofing.com | AF10: Not found for the owner. Only published address: matt.seaton@scissortailroofing.com — belongs to Matt Seaton, Director of Operations (NOT an owner); shown on homepage ("Call us at 405-928-8089 or email matt.seaton@scissortailroofing.com to describe your project") and About page; MX present (smtp.google.com)
A11: 20261012-10 | B11: Compassionate Care Veterinary Hospital of Charlotte | C11: Trish Johnson | D11: Practice Owner | E11: Not found. Secondary business numbers on BBB: (704) 847-4796 (phone) and (704) 847-7301 (fax) — distinct from the site's (704) 486-2571; not tied to the owner, do not treat as a direct line. | F11: +1 704-486-2571 | G11: Charlotte | H11: NC | I11: America/New_York (Eastern) | J11: Tue or Thu 10:00–11:30 AM ET (after the 7:30 check-in rush, before lunch), fallback Mon/Tue/Thu 4:30–5:20 PM ET near close. Never Wednesday (closed all day) and not Fri 12–2 PM (closed for lunch). Dr. Johnson is the only DVM listed, so she is in exam rooms most of the day — ask Teresa (Office Manager, 'most often the voice clients first hear') when Dr. Johnson takes vendor calls, or pitch Teresa as the champion. | K11: From the website (GBP not fetchable this run): 'Monday - Thursday: 7:30 am – 5:30 pm' but banner 'We are CLOSED all day on Wednesdays' / 'Wednesdays - Closed All Day'; 'Friday: 7:30 am – 12pm; 2 – 5:30pm'; 'Saturday and Sunday: Closed'. Net: open Mon, Tue, Thu 7:30–5:30, Fri 7:30–12 and 2–5:30; closed Wed, Sat, Sun. | L11: Who answers: Teresa Fesmire, Office Manager and Lead Receptionist — 'she is most often the voice clients first hear' (site); she also runs inventory. BBB separately lists 'Lynn Wingard, Practice Manager' (possibly stale — not on the current site; use Teresa). No answering service or IVR mentioned; after hours the line is not covered (site refers to outside ER). Dr. Johnson is the only DVM, so she is in rooms — Teresa is the realistic first contact and a natural champion (the niche playbook says go through the practice manager with a calm, low-pressure note). Ask for 'Dr. Johnson' by name; if unavailable, give Teresa the demo number and ask for a 5-minute window on Tue/Thu. Second published number: (704) 847-4796 (BBB) — may be an older main line; do not assume it is a direct line. No owner cell published. | M11: 65 | N11: Overwhelmed Owner-Operator (medium confidence; secondary: Growth-Minded Operator — hiring two roles) | O11: Free GEO audit (Chosen's matrix default for veterinary) — but open with the live voice-demo line built from charlottepetdoctor.com: the receptionist job post is the rubric's strongest door-opener and D2 = 15 (demo_build = yes). Use the GEO audit as ask #2 on the call/email. run_geo_audit = yes (D4 unchecked). | P11: 'Hi, this is Sam with Eat 4 Life Marketing — and full disclosure, this is a cold call, so you're welcome to hang up on me. I'm calling because your careers page is looking for a receptionist who can juggle several phone lines, and I noticed you're closed all day Wednesdays and weekends. We build a receptionist trained on Compassionate Care's own website — it picks up the calls that would hit voicemail, sends true emergencies straight to Carolina Veterinary Specialists, and books the rest for your front desk to confirm. Can I take 20 seconds to explain how it works, and then you decide whether it's worth a demo number you can call yourself?' (If Teresa answers: 'Hi, is this Teresa? Sam with Eat 4 Life Marketing — this is a cold call…' then same hook, and ask whether she or Dr. Johnson decides on front-desk tools.) | Q11: Missed-call / front-desk relief, not 'AI'. You are paying headcount to cover the phones and still have three closed days a week plus a Friday lunch gap; we build a receptionist trained on your own website that answers the calls that currently hit voicemail or a busy line, sends true emergencies straight to Carolina Veterinary Specialists (human/ER first, always), takes the rest as appointment requests Teresa confirms in the morning, and texts back every missed call in under a minute. Go-live is one conditional call-forwarding rule for missed/busy calls; rollback is one dial code. Proof lever: 'call the demo number we built from charlottepetdoctor.com before you pay anything.' Second ask: the free AI-visibility check for 'best vet in Charlotte' / 'emergency vet near Charlotte'. | R11: 'We're hiring a person for that' / 'Our clients want a real person' / 'An AI will mishandle an emergency.' Handle: it does not replace Teresa or the new hire — it only catches what already goes unanswered (Wednesdays, after 5:30, weekends, second line busy); emergencies are routed to a human or the ER immediately with no triage by the agent; they hear it themselves on the demo line first; nothing to set up beyond one call-forwarding rule. Secondary objection: 'GeniusVets handles our marketing' — answer that the voice line sits in front of the phone, not the website, and coexists with their site. | S11: The live Veterinary Receptionist posting (page last modified 2026-09-07 per sitemap.xml) that asks for 'Ability to multitask, managing several phone lines and several functions at once', paired with the hospital being closed all day Wednesdays and weekends while the homepage carries a '24/7 Emergency Info' button that sends callers to an outside ER. Source: https://www.charlottepetdoctor.com/about-us/careers/veterinary-receptionist and https://www.charlottepetdoctor.com/ | T11: hours_only — closed Wed/Sat/Sun and Fri 12–2; no answering service, call center, voicemail text, or AI receptionist mentioned anywhere on site or in page source. Homepage '24/7 Emergency Info' button leads to a referral page: 'For Emergency After Hours: Carolina Veterinary Specialists' (704) 815-3939 and 'For Urgent Care: Skyline Veterinary Specialists' (704) 612-5590. GBP hours/attributes not fetchable this run. | AA11: =IF(A11="","",IF(OR(V11="Game Plan Call booked",V11="Do not call",V11="Not interested",V11="Email captured (GEO audit)",X11="Game Plan Call booked",X11="Do not call",X11="Not interested",X11="Email captured (GEO audit)",Y11<>""),"Done",IF(W11<>"",W11+3,IF(U11<>"",U11+2,"Call today")))) | AE11: https://www.charlottepetdoctor.com | AF11: info@charlottepetdoctor.com
A12: 20261012-11 | B12: UB Code Roofing + | C12: Cynthia Smith | D12: President/CFO | E12: Not found (no number tied to Cynthia or Ronnie on any public page; the only numbers published are the company lines above) | F12: +1 303-458-3790 (BBB, Trustpilot, HomeAdvisor, Aurora Chamber). +1 303-225-4620 is the site number and is also listed beside Cynthia Smith on the Aurora Chamber member page, so it rings the business too; dial either, log which | G12: Aurora | H12: CO | I12: MT | J12: Tue-Thu 8:00-9:00 AM MT, right at office open and before Ronnie heads out (HomeAdvisor/Trustpilot reviews say Ronnie does inspections himself; Cynthia runs the office and insurance paperwork, so she is the one at the desk at 8). Fallback: Tue-Thu 4:00-4:45 PM MT before the 5 PM close. Skip Monday mornings (post-weekend storm backlog) and Saturdays (half day per site, closed per other listings). | K12: Site (/contact): Mon-Fri 8:00 AM-5:00 PM; Sat 8:00 AM-1:00 PM; Sun Closed; footer claims "We answer 7 days a week." Third-party listings differ: cityof.com shows Mon-Fri 8-5, Sat/Sun closed; Aurora Chamber shows Mon-Fri 8-4. Google Business Profile hours not verified. | L12: No office manager, dispatcher, or answering service named on the site, BBB, Chamber, Trustpilot, or HomeAdvisor. Cynthia Smith is the office: Aurora Chamber lists her as the member contact (with (303) 225-4620) and reviewers credit her with insurance and mortgage paperwork, so an 8 AM call likely reaches her directly. Ronnie Smith (VP, "the owner" to reviewers) is in the field; if he answers, pitch him as co-owner. Staff names seen in 2026 reviews: Jonathan and Ramone (crew/PM level, not phone). Lines: (303) 458-3790 (BBB/Trustpilot/HomeAdvisor main) and (303) 225-4620 (site and Chamber; Hibu phone-swap script present, but it is listed under Cynthia's name so it rings the business). After hours, expect voicemail (no 24/7 claim anywhere; callback form promises next business day); leave a 10-second voicemail naming the Trustpilot note "Ronnie and I could take that weight off your shoulders" and follow with the Podium text widget on the site. Open with "Is Cynthia in?" rather than asking for "the owner." Do not mention veteran status; do not quote Google review counts or Saturday hours as fact. | M12: 63 | N12: Family-Legacy Pride Brand (secondary: none strong; some Tech-Forward signals via Podium chat/text and claimed Trustpilot) | O12: Voice AI live demo line built from ubcoderoofing.com (door-opener: demo_build = yes; D2 = 15). Pair with missed-call text-back into their existing Podium/Hibu stack. Run the free GEO audit before send so the "Named in X of 28" line is available as the second ask. | P12: Hi, is this Cynthia? Cynthia, this is Sam with Eat 4 Life Marketing. Full disclosure, this is a cold call; you can hang up, or give me twenty seconds and decide. I was on ubcoderoofing.com and it says UB Code answers seven days a week, but your hours show Saturday ending at one and Sunday closed, so I got curious who catches the hail-damage calls after that, because that homeowner usually just calls the next roofer on Google. We build a receptionist trained on your own company that answers every one of those calls and books the inspection, and you can call the demo line and hear it before you pay a dollar. Can I take twenty seconds to show you how it works? | Q12: Ask for Cynthia or Ronnie by name; mention you read Cynthia's note that she and Ronnie "took that weight off" a customer's shoulders. Then: "Ronnie is on roofs doing inspections himself, and your site promises next-business-day callbacks, so the Saturday-afternoon and Sunday calls after a storm are landing on voicemail. We built a demo receptionist trained on your own website; call it, hear it book a roof inspection, and tell us if it sounds like UB Code." Close on the Game Plan Call or Cynthia's email for the demo number. | R12: "We already pay Hibu and Podium, our phones are handled." — Keep both; this only takes the calls that already roll to voicemail after 1pm Saturday and on Sundays, books them, and texts back every missed call, and you hear it on the demo line before anything changes. | S12: Cynthia's Oct 3, 2026 Trustpilot reply — "We're glad Ronnie and I could take that weight off your shoulders" (https://ca.trustpilot.com/review/ubcoderoofing.com) — paired with the neutral observation that the footer promises "We answer 7 days a week" while hours show Sunday closed (https://ubcoderoofing.com/contact). Opener in Sebastian's voice (under 25 words): "Cynthia, your note about taking the weight off a customer's shoulders stuck with me; who carries the Sunday calls when you and Ronnie can't?" | T12: Unknown / not stated. Published hours: "Mon - Fri: 8:00 am - 5:00 pm, Saturday: 8:00 am - 1:00 pm, Sunday: Closed" (https://ubcoderoofing.com/contact). Footer claims "Call (303) 225-4620 — We answer 7 days a week." and the emergency page says "Our team is ready to answer your call" and "Swift Emergency Responses", but there is no 24/7 claim and no mention anywhere (site, page source, BBB, Trustpilot) of an answering service, call center or AI receptionist. The Request Call Back form promises a representative "will contact you by the next business day" (https://ubcoderoofing.com/request-call-back). HomeAdvisor profile states "Emergency services are not offered." Podium text/webchat exists as a side channel. | AA12: =IF(A12="","",IF(OR(V12="Game Plan Call booked",V12="Do not call",V12="Not interested",V12="Email captured (GEO audit)",X12="Game Plan Call booked",X12="Do not call",X12="Not interested",X12="Email captured (GEO audit)",Y12<>""),"Done",IF(W12<>"",W12+3,IF(U12<>"",U12+2,"Call today")))) | AE12: https://ubcoderoofing.com | AF12: cynthia@ubcoderoofing.com
A13: 20261012-12 | B13: Eason Plumbing & Drain Cleaning | C13: Cody Eason | D13: Owner | E13: Not found (unlabeled second lines: +1 615-617-0513 on ProvenExpert next to the main line; +1 615-249-4851 in site service-page CTAs — neither tied to a named person) | F13: +1 615-971-3226 | G13: Lascassas (Murfreesboro / Rutherford County) | H13: TN | I13: America/Chicago (Central Time) | J13: Tue–Thu 7:00–7:45 AM CT, right at the posted 7am opening before trucks roll (owners are hands-on: a Google review on the site says 'Jeremy the owner was fantastic! One day service' and the About page shows 'Cody Eason - Hard at work'); second window 4:00–5:00 PM CT before the 5pm close. Never Sunday (closed). | K13: Site contact page: Monday–Friday 7:00am–5:00pm, Saturday 7:00–5:00pm, Sunday Closed (https://easonplumbing.com/contact-us/). Site also states 'We are available 24/7!'. Yelp (Lascassas listing, per search snippet) shows 'Open 24 hours' Mon–Sat, Sun closed — CONFLICT. Google Business Profile hours not retrieved this session. | L13: Main line +1 615-971-3226 is the only number on the site, BBB and Chamber; the office mailbox office@ exists so an office person likely answers during 7–5. No office manager or dispatcher is named anywhere public (no Team page, no signed review replies readable, no job posts). Ask for 'Cody' (BBB-listed Owner and TN SOS registered agent) or 'Jeremy' (customer-identified owner, ProvenExpert contact). Technician 'Thomas Duke' is named in two Google reviews on the site (not a decision-maker). Two unlabeled secondary numbers exist — +1 615-617-0513 (ProvenExpert) and +1 615-249-4851 (in 'Call Now' blocks on service pages, likely a tracking line) — do not treat either as a cell; dial the main line. | M13: 63 | N13: Family-Legacy Pride Brand (primary); Growth-Minded Operator (secondary). Confidence: medium (3+ signals across website, third-party profiles, reviews). | O13: Voice AI live demo built from easonplumbing.com — emergency/after-hours angle (24/7 promise vs 7–5 hours; burst-pipe season) with missed-call text-back; second lever: free AI Search Visibility audit (no FAQ schema; not named in 2 of 3 web-AI answers). | P13: "Cody? Sam with Eat 4 Life Marketing — this is a cold call, so feel free to hang up. I was on easonplumbing.com: it says you're available 24/7, but the posted hours stop at 5 and Sunday's closed. So who picks up when a pipe bursts on a Sunday night — you, voicemail, or nobody? We build a receptionist trained on your own site that answers and books those calls, and you can call the demo line before you pay a dollar. Can I take 20 seconds to explain, and you tell me if it's worth a longer look?" (If Jeremy answers, use his name; both are hands-on Easons.) | Q13: Legacy-protection + emergency coverage: three generations of Easons built the name; the calls that come in at 9pm Sunday or while Cody and Jeremy are under a sink are the ones that go to whoever answers next. Offer the demo line trained on their own site ('hear your business answered before you pay a dollar'), state plainly that go-live is one conditional call-forwarding rule for missed/busy calls and rollback is one dial code, and that it sits alongside Marketing 360 rather than replacing it. Mention gently that the Get-a-Quote page on the site is currently a blank placeholder form, so web quote requests have no path — E4L's speed-to-lead covers forms too. Ask #1 Game Plan Call; ask #2 email for the free AI visibility audit. | R13: 'We've got Marketing 360 / someone already handles our marketing' and 'our guys answer the phone / calls forward to a cell after hours.' Response: this isn't a website or ads product — it only catches what already rings out or hits voicemail, books it, and texts the caller back; it coexists with their current stack; nothing to set up beyond conditional forwarding; they can call the demo and try to break it first. Secondary: 'robot answering will embarrass us with a customer' — the demo is trained on their own story and hours; a human still answers whenever they can. | S13: Back-to-back 'Best Plumbing Company in Rutherford County' (2024 & 2025 Main Street Awards, stated on https://easonplumbing.com/) plus the Ruthies 2025 Community's Choice badge — the safest, freshest compliment; pair it with the 24/7-vs-7-to-5 observation. (Award dates not independently located; Murfreesboro Post list and DNJ gallery did not render.) | T13: Unstated. Site: 'We are available 24/7!' (footer, every page) and 'Our highly trained emergency plumbers are available 24/7 to help you.' (https://easonplumbing.com/emergency-plumber/) while posted hours are Mon–Sat 7:00am–5:00pm, Sunday Closed. Emergency page hedges: 'The response time can be from 30 minutes to 2 hours.' / 'This time of arrival also depends on staffing and queue of other plumbing emergencies.' No answering service, call center, or AI receptionist mentioned on the site or in page source. Yelp lists 'Open 24 hours' Mon–Sat (conflict with site hours). | AA13: =IF(A13="","",IF(OR(V13="Game Plan Call booked",V13="Do not call",V13="Not interested",V13="Email captured (GEO audit)",X13="Game Plan Call booked",X13="Do not call",X13="Not interested",X13="Email captured (GEO audit)",Y13<>""),"Done",IF(W13<>"",W13+3,IF(U13<>"",U13+2,"Call today")))) | AE13: https://easonplumbing.com | AF13: jeremy@easonplumbing.com — belongs to Jeremy Eason (ProvenExpert contact, re-verified 2026-10-13), NOT to Cody Eason; Cody has no published email. Any email must be addressed to Jeremy or to the Eason family, never to Cody at this address.
... A26: 20261012-25 | B26: Bill West Roofing, Inc. | C26: Bill West | D26: President | E26: Not found (neither published number is tied to Bill or Aaron by name on any page) | F26: +1 816-295-6299 (site header CTA 'Call Us for a Free Appointment', site JSON-LD telephone, CertainTeed profile, Project Map It). Second published line: +1 816-229-5215 (site footer, BBB profile). | G26: Grain Valley | H26: MO | I26: America/Chicago (Central Time) — Grain Valley, Jackson County, MO | J26: Tue–Thu 8:00–8:45 AM CT, right at opening (site hours Mon–Sat 8:00 a.m.–5:00 p.m.), before Aaron leaves for estimates and crews dispatch; fallback 4:00–5:00 PM CT when crews return. A site testimonial says 'Brittany in the office' handles customers, so the office line is staffed in hours — ask for Aaron first (customer-facing, runs estimates), Bill second. Dial +1 816-295-6299 (main CTA); +1 816-229-5215 is the footer/BBB line. Missouri follows federal 8 AM–9 PM; stay inside 8–5 CT. | K26: Mon–Sat 8:00 AM–5:00 PM, closed Sunday. Site footer: 'Monday thru Saturday 8-5:00 pm'; contact page: 'Mon-Sat: 8:00 a.m. – 5:00 p.m.'; site JSON-LD openingHoursSpecification Mon–Sat 08:00–17:00. GBP hours not reachable this run. | L26: In hours: 'Brittany in the office' (first name + role only, from a customer review embedded in the home page https://www.billwestroofing.com/ (JSON-LD review array / testimonial section) — NOT on /about-us/ — do not quote the review). After hours: an unnamed human answering service routes calls/messages to the team (https://www.billwestroofing.com/emergency-roof-repair/). Two published lines: +1 816-295-6299 (site header CTA + JSON-LD, CertainTeed, Project Map It) and +1 816-229-5215 (site footer, contact page, BBB — the only number BBB lists) — try the second if the first hits the service. No owner cell published. Contact form offers preferred callback windows including 'evening (4pm to 8pm)', so someone works callbacks after 5. To get through: ask for Aaron by first name (he runs estimates and is customer-facing), say it's about the after-hours emergency line, keep it to 20 seconds. | M26: 54 | N26: Family-Legacy Pride Brand (medium confidence); secondary cues of Tech-Forward (Roofr estimator, financing portal, SMS consent, monthly blog) | O26: Voice AI live demo line built from billwestroofing.com, positioned as the after-hours/overflow layer that qualifies storm callers (address, damage, insurance claim) and books the inspection — an upgrade of the current message-taking answering service, not a replacement for 'Brittany in the office'. Bundle missed-call text-back. Before first touch: run one GEO money question ('emergency roofer near Blue Springs, MO') on one platform to close the D4 gap and re-score. | P26: "Hi, is this Aaron? Aaron, it's Sam with Eat 4 Life Marketing — this is a cold call, so feel free to hang up on me. I was on billwestroofing.com this morning: fifty years, you and your dad, and right under the '24/7 Emergency Roof Repair' heading your hours say Monday to Saturday, 8 to 5. Right now the answering service takes a message on those night and Sunday storm calls — we build a receptionist trained on your own company that picks up instead, asks the homeowner the questions you'd ask, books the inspection, and texts back anyone you miss in under a minute. Can I take twenty seconds to explain how it works, and then you decide if it's worth calling the demo line we'd build for you?" (If Bill answers: 'Mr. West' and the same opener. If Brittany answers: 'Morning Brittany — Sam with Eat 4 Life Marketing, it's a cold call about the after-hours emergency line; is Aaron or Bill around for twenty seconds?') | Q26: Family-Legacy framing with an answering-service upgrade hook. Respect the name: 50 years, father and son, 'grows through referrals and name recognition'. Then the neutral observation: the home page says 24/7, the hours say Mon–Sat 8–5, and the emergency page says an answering service routes messages with a 24-hour response. A storm caller who gets a message-taker calls the next roofer who answers. E4L builds a receptionist trained on their own story that answers those calls, qualifies the homeowner (address, damage, insurance claim), books the inspection into their calendar, and texts back any missed call in under a minute — after-hours and overflow only, so Brittany and the office keep their day. Address Aaron (runs estimates, next generation) as the champion and Bill as the signer. Proof lever: 'hear it yourself on a demo number before you pay a dollar'. Never promise results; no prices on the call. | R26: 'We already have an answering service.' Answer: it takes a message and promises a callback within 24 hours; this one qualifies the caller, books the inspection and texts them back in under a minute — and you can call the demo line and judge it yourself before anything changes. Second objection: 'We grow on referrals, we don't do marketing.' Answer: this isn't marketing — it only catches the calls your referrals already generate when the office is closed or on a roof. | S26: The 50-year milestone (1976→2026, site's own count) plus the father-and-son story on /about-us/ and Aaron's 'better educated' quote — the safest, most specific compliment available. Pair it with the neutral phone observation: '24/7 Emergency Roof Repair' on the home page next to Mon–Sat 8–5 hours. Sources: https://www.billwestroofing.com/about-us/ and https://www.billwestroofing.com/ | T26: Hours Mon–Sat 8–5, closed Sunday. Home page advertises '24/7 Emergency Roof Repair' ('our emergency repair team swiftly responds'). Emergency page credits an unnamed human answering service: 'Provide prompt after-business hours responsiveness. Our answering service immediately routes your calls or messages to us.' and 'we guarantee a 24-hour immediate response' (a 24-hour callback window, not 24/7 live answering). 24/7 coverage NOT confirmed; no AI receptionist vendor in page source. Pitch becomes an upgrade/cost-replacement conversation: message-taking service vs. a receptionist trained on their site that qualifies and books. https://www.billwestroofing.com/emergency-roof-repair/ | AA26: =IF(A26="","",IF(OR(V26="Game Plan Call booked",V26="Do not call",V26="Not interested",V26="Email captured (GEO audit)",X26="Game Plan Call booked",X26="Do not call",X26="Not interested",X26="Email captured (GEO audit)",Y26<>""),"Done",IF(W26<>"",W26+3,IF(U26<>"",U26+2,"Call today")))) | AE26: https://www.billwestroofing.com | AF26: info@billwestroofing.com
AA27: =IF(A27="","",IF(OR(V27="Game Plan Call booked",V27="Do not call",V27="Not interested",V27="Email captured (GEO audit)",X27="Game Plan Call booked",X27="Do not call",X27="Not interested",X27="Email captured (GEO audit)",Y27<>""),"Done",IF(W27<>"",W27+3,IF(U27<>"",U27+2,"Call today"))))
AA28: =IF(A28="","",IF(OR(V28="Game Plan Call booked",V28="Do not call",V28="Not interested",V28="Email captured (GEO audit)",X28="Game Plan Call booked",X28="Do not call",X28="Not interested",X28="Email captured (GEO audit)",Y28<>""),"Done",IF(W28<>"",W28+3,IF(U28<>"",U28+2,"Call today"))))
AA29: =IF(A29="","",IF(OR(V29="Game Plan Call booked",V29="Do not call",V29="Not interested",V29="Email captured (GEO audit)",X29="Game Plan Call booked",X29="Do not call",X29="Not interested",X29="Email captured (GEO audit)",Y29<>""),"Done",IF(W29<>"",W29+3,IF(U29<>"",U29+2,"Call today"))))
AA30: =IF(A30="","",IF(OR(V30="Game Plan Call booked",V30="Do not call",V30="Not interested",V30="Email captured (GEO audit)",X30="Game Plan Call booked",X30="Do not call",X30="Not interested",X30="Email captured (GEO audit)",Y30<>""),"Done",IF(W30<>"",W30+3,IF(U30<>"",U30+2,"Call today"))))
AA31: =IF(A31="","",IF(OR(V31="Game Plan Call booked",V31="Do not call",V31="Not interested",V31="Email captured (GEO audit)",X31="Game Plan Call booked",X31="Do not call",X31="Not interested",X31="Email captured (GEO audit)",Y31<>""),"Done",IF(W31<>"",W31+3,IF(U31<>"",U31+2,"Call today"))))
A33: Work top to bottom (sorted by score). Cadence: Call 1 the day the batch lands (use Best Time to Call), Call 2 two days later (leave a voicemail), Call 3 three days after that, then the email bridge. Log every call the same day. Every call ends with ask #1 (Game Plan Call) or ask #2 (email for the free GEO audit) — log 'Email captured' and put the address in Email Captured.

Sheet Leads
A1: Lead ID | B1: Date Added | C1: Batch | D1: Review Decision | E1: Status | F1: Lead Score | G1: Score Band | H1: Company Name | I1: Owner First Name | J1: Owner Last Name | K1: Owner Title | L1: Owner Email | M1: Owner Email Type | N1: Owner Email Confidence | O1: Owner Direct Phone | P1: Company Phone | Q1: Niche | R1: Niche Segment | S1: City | T1: State | U1: Why Now | V1: Attitude Type | W1: Recommended Entry Offer | X1: First-Fit Tier | Y1: Suggested Subject Line | Z1: Personalized First Line | AA1: Call Angle | AB1: Likely Objection | AC1: Call Opener (20 sec) | AD1: Best Time to Call | AE1: Business Hours | AF1: Timezone | AG1: Gatekeeper Notes | AH1: Best Opening Moment | AI1: Pain Signals | AJ1: Trigger Events | AK1: Attitude Evidence | AL1: Owner Background | AM1: Owner Personality / Values Cues | AN1: Owner Role Type | AO1: Owner LinkedIn | AP1: Owner Other Socials | AQ1: Website | AR1: Company Email (generic) | AS1: Street Address | AT1: ZIP | AU1: Service Area | AV1: Google Maps URL | AW1: Google Rating | AX1: Review Count | AY1: Founded / Years in Business | AZ1: Team Size (est.) | BA1: Locations | BB1: Sub-services | BC1: Tech Adoption | BD1: Marketing Sophistication | BE1: Growth Stage | BF1: Review Response Behavior | BG1: After-Hours Handling | BH1: Online Booking | BI1: Chat / Text on Site | BJ1: Vendors Detected | BK1: Ads Running | BL1: AI Search Presence | BM1: Disqualifier Check | BN1: Score Breakdown | BO1: Evidence Links | BP1: Research Confidence | BQ1: Notes for Chosen | BR1: Reviewer Notes | BS1: GHL Contact ID | BT1: Loaded to GHL
A2: 20261012-01 | B2: 2026-10-12 | C2: 1 | E2: New | F2: 71 | G2: =IF(F2="","",IF(F2>=80,"A — send today",IF(F2>=60,"B — worth a touch",IF(F2>=40,"C — hold","D — reject")))) | H2: Howard Injury Law | I2: Glen | J2: Howard | K2: Attorney | L2: ghoward@howardinjurylaw.com | M2: Personal (named) | N2: Confirmed | O2: Not found (a client review says Glen shared his personal cell, but no direct line is published; main line +1 702-331-5722, fax +1 702-629-7161 per site and NV Bar) | P2: +1 702-331-5722 | Q2: Personal injury law | R2: core | S2: Las Vegas | T2: NV | U2: He is investing in traffic right now - eight blog posts updated Oct 12-13, 2026, a Spanish video campaign and /es/ landing pages, call tracking and a Meta pixel on the site - so more ad-driven and organic calls are landing on a single-attorney firm whose published after-hours plan is a chat widget and the owner's cell. In PI, one signed case is a $5k+ fee and an injured caller who hits voicemail dials the next firm. No event-driven trigger was found, so position this as a 'first voice layer' conversation rather than a reaction to something. | V2: Growth-Minded Operator (secondary: Tech-Forward Early Adopter) - confidence medium | W2: Free GEO audit (Chosen's matrix entry for PI law) paired with a bilingual (English/Spanish) AI voice-receptionist demo line built from howardinjurylaw.com; lead product on the Game Plan Call = AI voice receptionist with empathetic no-advice intake + missed-call text-back / speed-to-lead; GEO as the add-on. No prices in any asset. | X2: Own | Y2: who answers 'Talk with Glen' at 9pm? | Z2: Your homepage says 'Free Case Review - 24/7, Talk with Glen'; your contact page says Mon-Fri 9 to 5. Curious what covers that gap at 9pm. | AA2: Missed-call / after-hours bilingual intake is the wedge; the free GEO audit is the door-opener. Acknowledge he already pays for calls (CallRail tracking, Meta pixel, an ads agency) and that the site promises 24/7 in four languages with one attorney and three staff on a 9-to-5 office line. E4L's receptionist, trained on his own site, answers every missed or after-hours call, runs an empathetic intake (date of injury, treatment, insurer, no legal advice) in English or Spanish, books the consult, and texts back every missed call in under a minute - the caller never reaches the next firm on Google. Proof lever: a demo line built from howardinjurylaw.com he can call before paying anything. Respect his Intaker chat: it handles web chat/text, not the ringing phone. Never promise case volume or outcomes. | AB2: 'We're already covered 24/7 - we have Intaker chat and texting, and clients can reach me on my cell.' Answer: chat and text catch the people who type; the voice agent catches the ones who dial at 9pm and get voicemail, and it drops them into the same intake - go-live is one conditional call-forwarding rule on missed/busy calls. Second objection: 'We already have an agency (Storm Media) doing SEO and GEO' - the audit is free, show the screenshots, do not bash the agency; pivot to the phone. Third (PI-specific): 'I get pitched by marketing guys every day' - lead with the demo number and one verifiable observation, not a pitch. | AC2: "Hi Glen, this is Sam with Eat 4 Life Marketing - this is a cold call, so feel free to hang up on me. I was on howardinjurylaw.com last night: the header says 'Free Case Review, 24/7, Talk with Glen,' and your contact page says Monday to Friday, 9 to 5. When a crash victim calls at 9pm, or calls in Spanish, who picks up right now - you, voicemail, or nobody? We build an AI receptionist trained on your own site that answers those calls, does a no-advice intake in English or Spanish, and books the consult - and we put a demo line on the phone you can call before you pay a dollar. Can I take 20 seconds to tell you how it works, or should I just send the demo number to ghoward@?" | AD2: Tue-Thu 9:00-10:30 AM PT, right after the office opens at 9 and before Glen is on adjuster calls/court (he negotiates every bodily-injury case personally per the site FAQ schema); fallback Tue-Thu 4:00-4:45 PM PT before the 5 PM close. Avoid Mondays (post-weekend intake pile-up for a 3-person case team). The main line is CallRail-tracked and staffed by the case team during 9-5; ask for Glen by first name. | AE2: Office: 'Monday to Friday, 9AM to 5PM PST' (site contact block, https://www.howardinjurylaw.com/contact-us/ and footer). Same page/header also says 'Free Consultation · Available 24/7' and JSON-LD Attorney schema claims openingHours 'Mo,Tu,We,Th,Fr,Sa,Su 24/7' (00:00-23:59). Spanish page: 'De lunes a viernes, de 9:00 a 17:00 (hora del Pacifico)' vs 'Consulta gratuita las 24 horas, los 7 dias de la semana'. GBP hours not opened directly. | AF2: America/Los_Angeles - Pacific Time (PDT, UTC-7 in October); Las Vegas, NV | AG2: Main line +1 702-331-5722 is the office line (CallRail dynamic-swap tracked); no receptionist is named anywhere. Case team per About page (https://www.howardinjurylaw.com/about-us/): James Martin (15+ yrs legal field, role not stated; several Google reviews on the site name James, one calls him the case manager), Vanessa Kitchen (20+ yrs medical field, 10+ yrs practice administrator and marketing - most likely the office/ops lead and the best internal champion), Nathalie Sanabria (case manager). No answering service, call center or AI receptionist is credited; after hours the only named channel is the Intaker chat/text widget ('our 24/7 chat below'; YouTube bio '24/7 Help: intaker.com/howardinjurylaw/pi'). A Google review on the site says 'I had the lawyers personal cell number' - the cell is NOT published; do not ask for it. If the team answers: 'Hi, is Glen in? It's Sam - it's about the 24/7 line on the website.' If Vanessa answers, pitch her as champion (she ran a medical-practice front desk) and ask for 15 minutes with Glen. Careers page is 404; no job posts found (Indeed blocked), so no receptionist hire to reference. | AH2: The 24/7 promise on a one-attorney firm: homepage 'Free Case Review - 24/7 Talk with Glen!' and 'we're available 24/7 at (702) 331-5722' vs the contact block 'Monday to Friday, 9AM to 5PM PST' (https://www.howardinjurylaw.com/ and /contact-us/). Neutral, verifiable in 10 seconds, ties straight to the after-hours/bilingual intake gap. Secondary: his own 'we trained there' insurance-defense angle - he sells on knowing the other side's playbook, so frame E4L as showing him the caller's side of the phone. | AI2: (1) Hours gap, verbatim: 'Free Case Review - 24/7 Talk with Glen!' / 'we're available 24/7 at (702) 331-5722' vs 'Monday to Friday, 9AM to 5PM PST' (https://www.howardinjurylaw.com/, /contact-us/); Spanish page: 'Consulta gratuita las 24 horas, los 7 dias de la semana' vs 'De lunes a viernes, de 9:00 a 17:00 (hora del Pacifico)' (https://www.howardinjurylaw.com/es/). (2) Single attorney carrying the promise: FAQ schema 'Your bodily injury case is negotiated directly by attorney Glen A. Howard'; About page shows 1 attorney + 3 staff. (3) Owner's cell is the after-hours plan: review on site 'I had the lawyers personal cell number ... answered calls and questions within 24 hours' (https://www.howardinjurylaw.com/testimonials/) - 24 hours, not 60 seconds. (4) Bilingual promise with no named bilingual intake: homepage 'Our team serves clients in English, Spanish, Cantonese, and Mandarin' while the /es/ page names no Spanish-speaking staff member. (5) Paying for calls already (CallRail, Meta pixel, AdsBot allowance) with no phone coverage vendor named. No responsiveness complaints found in accessible reviews (they praise communication); Google lowest-rated, Yelp, Avvo and Indeed could not be opened. | AJ2: No dated trigger within 60 days found. Soft activity: 8 slip-and-fall blog posts updated 2026-10-12/13 and page-sitemap updated 2026-10-12 (https://www.howardinjurylaw.com/post-sitemap.xml); About-page images uploaded 2026-02 and 2026-03; Spanish video campaign uploaded 2025-11-19 and 'Better Call Howard' owner video 2025-09-25 (site JSON-LD); robots.txt created 2025-11-08; Wayback shows the site live 2022-12-23 and 2026-05-16 (redesign diff not possible - snapshot fetch 403; logo file dated 2024/10 suggests a 2024 refresh). Not checked: Indeed/ZipRecruiter (403), Meta Ad Library (blocked), Nevada SOS (JS-only), local news (search unavailable). Careers page 404. | AK2: (1) Paying for leads: CallRail dynamic number swap (cdn.callrail.com swap.js) and Meta pixel id 3636794976532839 in homepage source; robots.txt explicitly allows AdsBot-Google for / and /es/ (Google Ads landing-page crawler) - https://www.howardinjurylaw.com/ and /robots.txt, seen 2026-10-13. (2) Site actively invested in: post-sitemap shows 8 slip-and-fall posts updated 2026-10-12/13, page-sitemap 2026-10-12, About images uploaded 2026-02/03, Spanish /es/ section and Spanish video campaign (JSON-LD uploadDate 2025-11-19) - https://www.howardinjurylaw.com/post-sitemap.xml. (3) Tech adoption: Intaker 24/7 chat/intake widget, 'Text Us' sms: link, GTM, FAQPage/LegalService/Attorney/VideoObject/HowTo schema, agency credit 'Powered by Storm Media LLC' (SEO/web/paid ads/'SEO + GEO + AEO'). (4) Owner on camera: 'Better Call Howard' video (Glen urges victims to call before signing), YouTube channel with 5 firm videos incl. Spanish. (5) Growth posture: awards wall, 'Serving NV, CA, AZ, and CO', '$80M+ Recovered, 1,000+ Clients'. No negatives observed (BBB A+, 0 complaints in 3 years; no hostile replies seen - Google review replies not accessible). Sources: website + YouTube + BBB = 3 categories. | AL2: Self-stated on About page (https://www.howardinjurylaw.com/about-us/): raised in Cleveland; Ohio State University B.S. Resource Management 1998; two years as an executive consultant to Fortune 500 companies; Thomas Jefferson School of Law J.D. 2003; moved to Las Vegas 2003 and worked at a multi-state insurance defense firm; licensed in Nevada state and federal courts 2004 (NV Bar confirms admission 10/20/2004, Thomas Jefferson); Kring & Chung LLP 2005-2007; Jack Bernstein & Associates LLP, Senior Attorney 2007-2013; Bourassa Law Group, Senior Attorney 2013-2017; founded Howard Injury Law 2017. Homepage claims '$80M+ Recovered, 20+ Years, 1,000+ Clients'. Awards listed on site (awarding-org pages not verified): NAOPIA Top Ten Attorney 2022, Avvo Clients' Choice 2020, Super Lawyers 2021, National Trial Lawyers Top 100, Million Dollar Advocates Forum, U.S. News Best Law Firms, American Institute of Legal Counsel 10 Best (workers' comp). NV Bar: 'Disciplinary Actions: None.' | AM2: Tone: confident, direct, insider-angle with warmth. Verbatim site lines: 'We Know How Insurance Companies Think - Because We Trained There'; 'Glen Howard started his career on the insurance defense side. He learned their playbook, then switched sides. Now he uses it against them - for you.'; 'Free Case Review - 24/7 Talk with Glen!'; 'Las Vegas is diverse - your legal team should be too.' YouTube bio: 'Trust HOWARD. Get EmpHOWARD' and a 'Better Call Howard' video - likes a pun, comfortable on camera. Reviews repeatedly say 'like family' and praise Glen's communication ('extremely communicative and attentive'). Brags: only handles PI, defense-side experience, no fee unless we win, 4-language team, awards wall, 'Dedicated medical case manager'. Mirror: short, plain, specific; respect that he is pitched daily. | AN2: Owner-operator | AO2: Not found (no LinkedIn link on site; LinkedIn and web search were not reachable from this session) | AP2: Owner Avvo profile (linked from site): https://www.avvo.com/attorneys/89146-nv-glen-howard-1770669.html. Firm accounts linked in site footer: https://www.facebook.com/howardinjurylaw, https://www.instagram.com/howard.injury.law/, https://www.tiktok.com/@howard.injury.law, https://www.youtube.com/@HowardInjuryLaw (31 subscribers; Glen on camera in 'Better Call Howard', uploaded 2025-09-25 per site JSON-LD), https://x.com/HowardInjuryLV. Follower counts/post recency for FB/IG/TikTok/X could not be opened (blocked). | AQ2: https://www.howardinjurylaw.com | AR2: Not found (only ghoward@howardinjurylaw.com is published; no info@/office@ anywhere on site, NV Bar or BBB) | AS2: 6330 Spring Mountain Rd. Suite D, Las Vegas, NV 89146 (site contact block, NV State Bar record and BBB all agree) | AT2: 89146 | AU2: Contact page: 'Serving All of Nevada & Surrounding Areas' - Las Vegas Strip, Downtown, Henderson, North Las Vegas, Reno/Lake Tahoe, Paradise, Spring Valley, Enterprise, Summerlin, Pahrump, Mesquite, Elko, Boulder City, East Las Vegas, Laughlin, Ely, Beatty, plus California, Arizona, Colorado; YouTube bio: 'Serving NV, CA, AZ, and CO' | AV2: https://maps.app.goo.gl/s24pLXgDGgEK61R8A (review link on site); https://www.google.com/maps/place/Howard+Injury+Law/@36.1259265,-115.2301308,17z | AW2: 4.9 (site JSON-LD AggregateRating on https://www.howardinjurylaw.com/; GBP not opened directly - Maps is JS-only from this session) | AX2: 122 (site JSON-LD reviewCount; newest embedded Google reviews dated 2026-02, 2026-01, 2025-07; GBP not opened directly) | AY2: 2017 (About page: 'Howard Injury Law, Partner/Owner, Personal Injury Since 2017'; domain registered 2017-05-31 per RDAP; BBB structured data foundingDate 2017-05-16). Glen admitted to NV Bar 10/20/2004. | AZ2: 4 - 1 attorney (Glen A. Howard) + 3 named staff on About page: James Martin (15+ yrs legal field, role not stated), Vanessa Kitchen (20+ yrs medical field, 10+ yrs practice administrator/marketing, title not stated), Nathalie Sanabria (case manager) | BA2: 1 (6330 Spring Mountain Rd Ste D; single address on site, NV Bar and BBB) | BB2: Motor vehicle accidents (car, rear-end, head-on, rollover, T-bone, motorcycle, trucking, rideshare/taxi, DUI, pedestrian, e-bike/e-scooter, bicycle, hit & run, bus, boat, vehicle defects); premises liability (slip & fall, casino injury, foodborne illness, dog/animal attack); workers' comp third-party; wrongful death; catastrophic injury; product defects; medical malpractice / hospital negligence. Spanish-language /es/ section. | BC2: advanced - Intaker chat/intake widget (intaker.azureedge.net/widget/chat.min.js), click-to-text (sms:7023315722), CallRail call tracking, Google Tag Manager/gtag, Meta pixel, reCAPTCHA form, rich JSON-LD (FAQPage, LegalService+AggregateRating, Attorney, VideoObject, HowTo), WordPress/Elementor, Google Workspace mail (MX aspmx.l.google.com). No online scheduler detected. | BD2: agency_managed - footer 'Powered by Storm Media LLC' (stormmedia.digital: SEO, web, Meta/Google paid ads, 'SEO + GEO + AEO', YouTube/GBP management; general agency, gmail contact, no law-firm specialty stated); CallRail + Meta pixel + AdsBot allowance; branded video content in English and Spanish; blog actively updated. | BE2: established - founded 2017, 122 Google reviews at 4.9 (site JSON-LD) with reviews dated Jan-Feb 2026, stable 4-person team, single office, multi-state service claims; no hiring evidence (careers 404, Indeed blocked). | BF2: unknown - Google review replies could not be opened (Maps JS-only), Yelp and Avvo returned 403; BBB shows 0 complaints in 3 years and 0 BBB reviews. | BG2: Site claims 'Available 24/7', 'Free Case Review - 24/7 Talk with Glen!' and 'Give us a call, we're available 24/7 at (702) 331-5722' while the contact block lists office hours 'Monday to Friday, 9AM to 5PM PST'. No answering service, call center or AI receptionist is named on the site, in page source, on BBB or on YouTube. The only named 24/7 channel is the Intaker chat/text widget ('fill out our simple form or our 24/7 chat below'; YouTube bio '24/7 Help: https://www.intaker.com/howardinjurylaw/pi') - chat/SMS, not phone. A client review on the site says 'I had the lawyers personal cell number', suggesting after-hours calls fall to Glen's own cell. GBP hours not opened directly. | BH2: None - no Calendly/Acuity/Clio Scheduler or any scheduler script in source. Intake is via the Intaker chat ('Check If You Have A Valid Personal Injury Claim'), a reCAPTCHA contact form ('Submit for Your FREE Attorney Case Evaluation', no response-time promise shown), 'Start My Free Case Evaluation' link, phone, and text. | BI2: Yes - Intaker chat/intake widget on every page (intaker.com/howardinjurylaw/pi; Intaker markets an 'AI intake engine' and 'AI Texting Agent' - whether this firm uses the AI texting tier is unverified) plus a 'Text Us' header link (sms:7023315722) and 'Envianos un Texto' on /es/. | BJ2: WordPress + Elementor; Storm Media LLC (agency credit, https://www.stormmedia.digital/); CallRail (cdn.callrail.com swap.js); Google Tag Manager / gtag; Meta pixel (id 3636794976532839); Intaker chat/intake (intaker.azureedge.net); Google reCAPTCHA; Google Workspace (MX); Squarespace Domains (registrar, RDAP); YouTube embeds; Avvo attorney profile. Not detected: Smith.ai, Ruby, AnswerConnect, Podium, Birdeye, Clio widgets, Lawmatics, Ngage/ApexChat, Scorpion, FindLaw, Justia, Hibu, Thryv. | BK2: Likely but unverified as active: CallRail dynamic number swap + Meta pixel on the homepage, robots.txt (created 2025-11-08) allows AdsBot-Google for / and /es/ (the Google Ads landing-page crawler), and the credited agency sells Meta/Google paid ads. Meta Ad Library and Google Ads Transparency Center could not be opened from this session (JS/403), and no Sponsored SERP could be checked (search budget exhausted). No Google LSA badge check possible. | BL2: not checked - ChatGPT/Perplexity/Gemini spot-check could not be run this session (web search budget exhausted; AI platforms not reachable via fetch). Schema check done: site already carries FAQPage, LegalService (AggregateRating 4.9/122 + Review), Attorney (LocalBusiness-type with 24/7 openingHours), VideoObject, HowTo and BreadcrumbList JSON-LD, and the agency advertises 'GEO + AEO' - run the full 28-answer GEO audit before first touch; expect partial presence rather than 0-of-28. | BM2: PASS - Not a chain/franchise/PE-owned (single office; NV Bar firm 'Law Offices of Glen A. Howard'; no group language). Working own-domain site (HTTP 200, actively updated). Live US business (NV Bar 'ATTORNEY Active', 'Disciplinary Actions: None'; BBB A+, 0 complaints; site edited 2026-10-12/13). Inbound channels exist (phone, text, chat, form). Not a competitor/non-buyer category. Not automated on both fronts: no AI phone agent credited (Intaker is chat/SMS); AI-answer presence unchecked. Suppression.csv and seen.csv: 0 hits for 'howardinjurylaw' and 'Howard'. Not done from this session: GHL 'E4L Services' dedupe via ghl-contacts.js and Nevada SOS entity status (JS-only portal) - run both before loading. | BN2: D1 Decision-maker reach: 20/20 - Glen A. Howard, Esq., 'Partner/Owner ... Since 2017' (https://www.howardinjurylaw.com/about-us/) corroborated by NV State Bar #9065 'ATTORNEY Active', firm 'Law Offices of Glen A. Howard', same address/phone (https://nvbar.org/for-the-public/find-a-lawyer/?usearch=Glen%20Howard) and BBB 'Glen A. Howard, Attorney'; personal email ghoward@howardinjurylaw.com published as mailto + JSON-LD on the site, MX present (Google); secondary channel = owner Avvo profile linked from site + firm X/IG/TikTok/YouTube; LinkedIn not found. | D2 Phone-coverage gap: 15/15 - phone-first (header '(702) 331-5722', hero 'Call Us for a Free Consultation', '24/7 Talk with Glen!', 13 tel: links, sms link) + gap proofs: PI law is on the inherent-urgency list; office hours 'Monday to Friday, 9AM to 5PM PST' narrower than the 'Available 24/7' claim; no answering service/call center/AI receptionist named anywhere (only Intaker chat). | D3 Lead-response leak: 0/15 - accessible reviews praise responsiveness ('answered calls and questions within 24 hours', 'very easy to get ahold of', 'always available to answer my questions' - https://www.howardinjurylaw.com/testimonials/); site has 24/7 chat + text + form (no friction signal); careers 404; BBB 0 complaints; checked but blocked: Google lowest-rated reviews, Yelp (403), Avvo (403), Indeed (403). | D4 AI visibility gap: 0/10 NO EVIDENCE - no AI platform could be checked this session; schema already present (FAQPage, LegalService, Attorney, VideoObject, HowTo), so even a 0-of-6 result would cap at 6. | D5 ICP fit / ability to pay: 15/15 - independent single-office owner-named firm; PI law on list; proxies: since 2017 (About, RDAP 2017-05-31, BBB 2017-05-16), 122 reviews at 4.9 with Jan-Feb 2026 reviews, 3 named staff + attorney, PI ticket $5k+ row and '$80M+ Recovered / 1,000+ Clients' claim, statewide + CA/AZ/CO service area. | D6 Buying signals: 11/15 - paid-media signal (a): CallRail dynamic number swap on landing pages + AdsBot-Google allowance in robots.txt; spend group (d): GTM + Meta pixel + CallRail + agency credit (Storm Media); (e): Intaker paid intake tool; no dated trigger within 60 days (only soft content activity 2026-10-12/13); Meta Ad Library/Ads Transparency/LSA not checkable. | D7 Owner attitude / stack: 10/10 - net 3 positives: modern actively-updated site (images 2026-02/03, sitemap 2026-10), tech adoption (text, chat, call tracking, schema), growth posture (owner on camera, awards wall, multi-state claims); no negatives observed; Storm Media is a small general agency (gmail contact), not a bundled vertical incumbent, but it advertises 'SEO + GEO + AEO' - flag GEO overlap. TOTAL 71 = QUALIFIED (TRUSTED: disqualifier pass recorded, 6 of 7 dimensions carry evidence or a logged null, D1 positive, D2 direct quoted hours string, D5 cited). Not eligible for SEND TODAY until the D4 AI spot-check is run. | BO2: https://www.howardinjurylaw.com/, https://www.howardinjurylaw.com/about-us/, https://www.howardinjurylaw.com/contact-us/, https://nvbar.org/for-the-public/find-a-lawyer/?usearch=Glen%20Howard, https://www.bbb.org/us/nv/las-vegas/profile/personal-injury-lawyer/howard-injury-law-1086-90094513, https://www.howardinjurylaw.com/testimonials/, https://www.howardinjurylaw.com/es/, https://www.howardinjurylaw.com/robots.txt, https://www.howardinjurylaw.com/post-sitemap.xml, https://www.howardinjurylaw.com/page-sitemap.xml, https://www.youtube.com/@HowardInjuryLaw, https://www.intaker.com/howardinjurylaw/pi, https://www.intaker.com/, https://www.stormmedia.digital/, https://www.avvo.com/attorneys/89146-nv-glen-howard-1770669.html, https://rdap.verisign.com/com/v1/domain/howardinjurylaw.com, https://dns.google/resolve?name=howardinjurylaw.com&type=MX, https://maps.app.goo.gl/s24pLXgDGgEK61R8A, https://www.google.com/maps/place/Howard+Injury+Law/@36.1259265,-115.2301308,17z, https://www.howardinjurylaw.com/blog/, https://www.facebook.com/howardinjurylaw, https://www.instagram.com/howard.injury.law/, https://www.tiktok.com/@howard.injury.law, https://x.com/HowardInjuryLV, http://web.archive.org/web/20221223123253/https://www.howardinjurylaw.com/, http://web.archive.org/web/20260516232423/https://www.howardinjurylaw.com/ | BP2: Medium | BQ2: Title detail: Attorney, Partner/Owner (About page: 'Meet Glen Howard, ESQ.' and experience list 'Howard Injury Law, Partner/Owner, Personal Injury Since 2017'); NV State Bar #9065, 'ATTORNEY Active', member since 10/20/2004, firm 'Law Offices of Glen A. Howard'; BBB lists 'Glen A. Howard, Attorney'. Legal entity note: NV Bar firm name: Law Offices of Glen A. Howard. Band: QUALIFIED (71, TRUSTED) - not SEND TODAY only because the D4 AI spot-check could not be run this session; run the 28-answer GEO audit and build the bilingual voice demo before first touch, then re-band. Route: email-first to ghoward@ (Confirmed personal email, Google Workspace MX) with Sam's call within 48h, Tue-Thu 9-10:30 AM PT. Compliance: legal vertical - no outcomes, no legal advice, no case-volume promises; never quote the 'personal cell' review back to him or name reviewers. Watch-outs: (1) Storm Media (his agency) advertises 'SEO + GEO + AEO' and the site already has FAQ/LegalService/Attorney schema - expect the GEO audit to show partial presence; the phone gap is the cleaner wedge. (2) Intaker sells an 'AI Texting Agent' - confirm on the call whether he uses it before pitching missed-call text-back as new. (3) Demo must handle Spanish at minimum (site also promises Cantonese and Mandarin). (4) Vanessa Kitchen (ex-practice administrator with marketing background) is the likely internal champion. Not verifiable this session (blocked/403/JS): Google review replies and lowest-rated reviews, Yelp, Avvo, Indeed/job posts, Meta Ad Library, Google Ads Transparency, LSA badge, LinkedIn, Nevada SOS, Facebook/Instagram/TikTok recency - refresh D3/D6 if a slot depends on them.
A3: 20261012-02 | B3: 2026-10-12 | C3: 1 | E3: New | F3: 69 | G3: =IF(F3="","",IF(F3>=80,"A — send today",IF(F3>=60,"B — worth a touch",IF(F3>=40,"C — hold","D — reject")))) | H3: Viking Heating & Air Conditioning | I3: Nicole | J3: Bridge | K3: Owner / Member | L3: info@viking-hvac.com (generic office mailbox; present only in the company's JSON-LD page source on blog.viking-hvac.com and blog.viking-hvac.com/careers, not as visible text; no owner-personal email found on any public page) | M3: Generic (info@/office@) | N3: Likely | O3: Not found | P3: +1 480-689-5167 | Q3: HVAC | R3: core | S3: Chandler | T3: AZ | U3: A live dispatcher opening, 10 new Google reviews in Oct 2-9, 2026, and near-daily fall tune-up posts mean call volume is up and they are paying headcount for phones this week; the heating-season emergency window is the wedge. | V3: Growth-Minded Operator | W3: Voice AI live demo built from viking-hvac.com (DEMO PATH, call-first to Sam with the demo number; email to info@ only as a gatekeeper-friendly second touch), framed on heating-season tune-up volume and the open dispatcher seat; add missed-call text-back. Do not lead with GEO - FAQ schema and an active blog already exist. | X3: Recover | Y3: Viking's dispatcher opening and after-hours calls | Z3: Saw Viking is hiring a dispatcher to run the daily board while your site promises 24/7 emergency service across 36 cities, so who's catching the no-cool calls once the office clears out? | AA3: Nikki, you're hiring a dispatcher at $21-25 an hour and telling 36 cities you're there 24/7. We built a receptionist demo from viking-hvac.com you can call right now: it picks up the calls that ring while your dispatcher is on another line or after hours, qualifies the no-cool emergency, and books it so nothing waits for the morning. Go-live is one call-forwarding rule for missed and busy calls, rollback is one dial code, and it can hand bookings to your existing Service Fusion setup. | AB3: 'We run Service Fusion and we're hiring a dispatcher - we're covered.' Answer: keep both; this only takes the calls that would otherwise hit voicemail (busy, after hours, weekends) and hands the booking back to your dispatcher, so nothing changes for the team during the day - call the demo and judge it yourself before anything is bought. | AC3: Nikki? Sam with Eat 4 Life Marketing out of LA - and this is a cold call, so feel free to hang up on me. I was on Viking's careers page: you're hiring a dispatcher to run the daily board while the site promises 24/7 emergency service across 36 cities. We built a receptionist demo trained on viking-hvac.com that picks up the no-cool calls that ring while your dispatcher is on another line or after the office clears out, and books them. Can I take twenty seconds to tell you how it works, and you decide if it's worth a longer look? | AD3: Tue-Thu 7:30-8:30 AM AZ (same as LA time until Nov 1): a one-office shop builds the day's dispatch board then, and with the dispatcher seat open the person on the main line is most likely Nikki (Member/Owner, registered agent, office side) rather than a hired gatekeeper. Second window Tue-Thu 4:00-5:30 PM AZ when Kelly (HVAC Tech/Owner) is back from the field. Avoid 9 AM-3 PM, when the line is fielding same-day no-cool calls during fall tune-up season, and avoid Mondays (weekend backlog) and Friday afternoons. | AE3: No office hours published on viking-hvac.com, the careers page or BBB. Homepage and blog JSON-LD say open 00:00-23:59 Mon-Sun, and the Google Business Profile mirror (serviceagent.ai) shows 'Open 24 hours' every day with a 'Direct line - speak to a representative'; the site markets '24/7 emergency service' with 'emergency technicians always on call'. In practice it is a one-office shop whose dispatcher role is 'full-time, in-person' running a daily board, so treat the office as weekday daytime (roughly 7 AM-5 PM AZ) with the 24/7 line layered on top. | AF3: AZ (Arizona, MST year-round, no DST; same clock as Los Angeles until Nov 1, 2026, then one hour ahead of LA) | AG3: Main line 480-689-5167 is the only number anywhere (site header, contact page, careers page, BBB, BuildZoom); CallRail is in the site code but the number matches every third-party record, so it is the real line, not a swapped tracking number. No office manager, receptionist, dispatcher or answering-service name is public, and the HVAC Dispatcher seat is currently open (full-time, in-person), so expect Nikki/Nicole Bridge or whoever is covering the board to pick up; no third-party answering service is mentioned anywhere. Kelly Bridge is 'HVAC Tech./Owner' and in the field - do not expect him midday. Ask for 'Nikki' (their own careers page uses that name; BBB has 'Nicole E. Bridge'). If a tech or fill-in answers: 'Is Nikki in the office this morning? It's about the dispatcher opening on your careers page' - true and specific. Their careers page brags 'Decisions made by people you actually know - Nikki and Kelly - not a call center in another state', so position the demo as backup for after hours and busy lines, never as replacing the dispatcher. No owner cell published; no 'no solicitation' notice seen. Second touch only: info@viking-hvac.com (generic, from their JSON-LD) addressed to Nikki or Kelly. Do not cite the Oct 2025 commercial-expansion press release (now 404); a tech named Logan Bridge appears in a recent review - do not assume a family relation. | AH3: The live 'HVAC Dispatcher' post ($21-25/hr, 'running the daily dispatch board') paired with the careers line 'Decisions made by people you actually know - Nikki and Kelly - not a call center in another state' (https://blog.viking-hvac.com/careers, seen 2026-10-12): they are hiring for the phone seat and proud that calls stay local, which is exactly the after-hours gap the demo covers without replacing anyone. | AI3: (1) JOB POST: 'HVAC Dispatcher - $21 - $25/hr - Full-time, in-person - Requires 3+ years of HVAC dispatching experience and running the daily dispatch board' plus 'Senior HVAC Service Technician - Urgently Hiring' (https://blog.viking-hvac.com/careers, seen 2026-10-12; no posting date shown). (2) 24/7 PROMISE, NO STATED COVERAGE: 'we provide 24/7 emergency HVAC services throughout our entire service area' and schema hours 00:00-23:59 daily, with no answering service/AI/call center named and no hours on the site (https://www.viking-hvac.com/). (3) BOOKING FRICTION: no online scheduling, no chat/text; form promise is only 'No obligation. Fast response.' with no stated turnaround (https://www.viking-hvac.com/contact-us/). (4) VOLUME: 10 new Google reviews Oct 2-9, 2026 and 36-city service area = call load at a one-office shop. Null: no reachability complaints found in the 10 reviews visible on-site; Google reply rate, Yelp, BBB complaints (0) showed nothing. | AJ3: (a) Live HVAC Dispatcher opening and 3 other roles (Senior Service Tech 'Urgently Hiring', Install Tech, Sales Rep) - https://blog.viking-hvac.com/careers, 2026-10-12, undated post. (b) Review spike: 10 Google reviews dated Oct 2-9, 2026 (Trustindex widget). (c) Seasonal: fall tune-up season now - reviews Oct 6, 2026 mention 'fall checkup', LinkedIn posts Oct 1-10, 2026 about fall tune-ups/blower motors. (d) Content push: blog post dated 2026-10-12; 8 LinkedIn posts in 10 days. (e) STALE: Oct 8, 2025 press release 'Viking HVAC expands commercial services in Phoenix Valley' (scout capture; URL returns 404 as of 2026-10-12). No ownership change, no new site (same domain), no negative review spike found. | AK3: (1) Hiring 4 roles incl. production and a dispatcher; Senior Service Tech tagged 'Urgently Hiring'; 'a family-owned team that's growing across the East Valley' - https://blog.viking-hvac.com/careers (2026-10-12). (2) Review velocity: 10 Google reviews dated Oct 2-9, 2026 in the Trustindex widget; 481 total - https://www.viking-hvac.com/ (2026-10-12). (3) Paid-traffic instrumentation: contact form captures GCLID, UTM, GA client id and CallRail session id; Meta pixel 826526979159085 + GTM in source - https://www.viking-hvac.com/contact-us/ and homepage source (2026-10-12). (4) Content cadence: 8 LinkedIn company posts Oct 1-10, 2026; blog post dated 2026-10-12 - https://www.linkedin.com/company/viking-heating-and-air-conditioning, https://blog.viking-hvac.com/ (2026-10-12). (5) Modern site: copyright 2026, HVACBusiness + FAQPage JSON-LD, financing, Service Fusion portal - homepage source. (6) Commercial expansion PR Oct 8, 2025 (scout capture; URL now 404). Signals span 4 source categories, no contradicting signal -> high confidence. Secondary flavor: family-owned pride ('The Bridge Between You and Comfort'). | AL3: Family-owned HVAC company founded 2016 in Chandler (BBB founded 2016-03-10; site 'since 2016'; homepage JSON-LD founder 'Nikki Bridge'). Kelly Bridge is listed on the ROC-derived BuildZoom record as 'HVAC Tech./Owner' (owner in the field); Nicole Bridge as 'Member/Owner' and is the LLC's registered agent. License qualifying party is Joel Montoya (not an owner). Company slogan 'The Bridge Between You and Comfort' (plays on the surname). 'Over 40 years of combined experience' (LinkedIn/site). Prior career, military service, trade school, podcasts/interviews: Not found (owner-level search not possible this run). | AM3: Plain-spoken, anti-corporate, family-culture voice. Careers page: 'We're not corporate. We're not chaotic.'; 'We believe in family culture, but high standards. We win together or we don't win at all.'; 'Decisions made by people you actually know - Nikki and Kelly - not a call center in another state.' About page values: 'Be honest, fair, on time, empathetic, helpful, diligent, and excellent'; promises no hassling, no falsified repairs, no upselling; 'free second opinion'; '100% satisfaction guaranteed'. Brags: '350+ 5 Star Reviews' hero, 'Best of business rate 2024/2025' badges (issuer not identified), Mitsubishi Diamond Contractor, 'Serving 29+ cities'. Review replies: not readable this run (Google reply data not rendered). Note: their own pages use both 'Nicole' (formal credit) and 'Nikki' (casual line, schema founder). | AN3: Owner-operator | AO3: Not found (search budget exhausted before owner X-ray; company page only: https://www.linkedin.com/company/viking-heating-and-air-conditioning - 17 followers, 11-50 employees) | AP3: Company accounts only (from site footer/BBB): https://www.facebook.com/vikingheatingandair/ (login-walled), https://www.instagram.com/vikingheatingandair/, https://x.com/Viking_HVAC, https://www.youtube.com/channel/UCV-2oM3WbSJiZhnPEudSVhw. No owner-personal accounts found. | AQ3: https://www.viking-hvac.com/ | AR3: info@viking-hvac.com (published in the company's own JSON-LD on blog.viking-hvac.com/careers and blog.viking-hvac.com; not shown as visible text on viking-hvac.com; MX not verified - no DNS tool in sandbox) | AS3: 3225 N Arizona Ave Ste C-12 | AT3: 85225 | AU3: Chandler HQ; Gilbert, Mesa, Phoenix, Scottsdale, Tempe, Queen Creek, Ahwatukee plus 'Maricopa County and parts of Pinal County'; 36 city pages (site also has Tucson-area pages: Marana, Oro Valley, Sahuarita, South Tucson); BBB: 'Valley Wide' | AV3: https://www.google.com/maps/search/?api=1&query=Google&query_place_id=ChIJYXSnVIcHK4cRsYunCS6JiyU | AW3: 4.9 (AggregateRating in the site's Trustindex JSON-LD, 2026-10-12; also 4.9 on ServiceAgent directory) | AX3: 485 Google reviews per homepage JSON-LD AggregateRating (ratingCount 485, 2026-10-12); ServiceAgent mirror shows a stale 355 | AY3: 2016 (BBB foundingDate March 10, 2016; site 'since 2016'; schema foundingDate 2016) - about 10 years; 'over 40 years of combined experience' | AZ3: LinkedIn company page: 11-50 employees; four open roles on careers page; technicians named in Oct 2026 reviews: Owen, Scott, Logan Bridge | BA3: 1 (Chandler HQ; 36 city landing pages in location-sitemap.xml) | BB3: Residential AC repair (24/7 emergency claim), AC/heat pump installation, heating repair, preventative maintenance ('Residential Service Plans' and 'Commercial Maintenance Plans'), ductwork, indoor air quality/air scrubbers, thermostat installation, swamp cooler services, commercial HVAC (retail, restaurant, manufacturing, healthcare, retrofits, ventilation), refrigeration (per BBB description), financing via unnamed partners, Mitsubishi Electric Diamond Contractor | BC3: modern - Service Fusion customer portal (app.servicefusion.com/vikingair), CallRail call tracking, Meta pixel + GTM/gtag, Trustindex Google review widget, SMS marketing opt-in on form, online financing application, FAQPage/HVACBusiness schema; but no online booking and no chat/text widget | BD3: agency_managed (unnamed vendor likely) - CallRail + GCLID/UTM capture, Meta pixel, Trustindex, near-daily LinkedIn posts (8 in Oct 1-10, 2026) and automated weather-triggered blog posts on a separate Next.js app at blog.viking-hvac.com (author 'Organization', post dated 2026-10-12); no agency credit in footer; no named marketing staff | BE3: scaling | BF3: unknown (Google owner replies not renderable this run; BBB has 0 reviews/0 complaints; Yelp blocked) | BG3: Unknown who answers after hours. Site claims: 'available 24/7' (repairs), 'we provide 24/7 emergency HVAC services throughout our entire service area' (FAQ), 'same-day service available for urgent situations'; homepage JSON-LD OpeningHoursSpecification Mon-Sun opens 00:00 closes 23:59; ServiceAgent mirror of GBP: 'Open 24 hours' every day (not verified on Google directly). No visible business hours on the site. No answering service, call center, or AI receptionist mentioned anywhere on site or in page source. Careers: 'not a call center in another state'; the dispatcher role is in-person and 'runs the daily dispatch board' (daytime). Gap = 24/7 promise with no stated after-hours answering mechanism. | BH3: N - 'Schedule Service' buttons link to /contact-us/ form ('Get My Free Quote'); no booking vendor scripts in source; only a Service Fusion customer 'Login' portal for existing customers | BI3: None - no chat widget or text-us button in page source (no tidio/intercom/podium/birdeye/drift/tawk); the form has an SMS marketing opt-in checkbox only | BJ3: WordPress (wp-content; Themeco-style 'x-anchor' classes; perfmatters plugin; HestiaCP hosting per robots.txt); Trustindex Google review widget; CallRail (calltrk/callrail session cookie capture in form); Google Tag Manager + gtag; Meta pixel (id 826526979159085); Service Fusion field-service/customer portal; blog.viking-hvac.com on Next.js with Wix-hosted images (wixstatic) - separate content platform; financing partner unnamed; Mitsubishi Diamond Contractor badge; no agency credit in footer; no booking or chat vendor | BK3: Not confirmed. Google Ads Transparency Center page showed no data (JS-rendered); Meta Ad Library returned 403; no Sponsored unit or LSA/Google Guaranteed badge observed (SERP check not possible this run). Indirect: contact form captures GCLID/UTM/CallRail session ids and a Meta pixel fires, i.e. the site is instrumented for paid traffic. | BL3: Not checked - the run's WebSearch budget was exhausted before the D4 spot-check, so no ChatGPT/Perplexity/Gemini answer was observed (D4 scored 0, NO EVIDENCE). Note for a later audit: homepage already carries FAQPage (7 Q&As) and HVACBusiness JSON-LD, so D4 would cap at 6 even if named in 0 answers; lead with the voice demo, not GEO. | BM3: PASS (2026-10-12). Legal entity: VIKING HEATING AND AIR CONDITIONING, LLC, Arizona domestic LLC L20751017, status Active, registered agent Nicole Bridge at 3225 N Arizona Ave Ste C-12 Chandler (OpenCorporates mirror of AZCC). License: ROC 316534 Specialty Dual, active per BuildZoom (ROC portal did not render without JS); older ROC 219012 Specialty Residential inactive. BBB A+ (not accredited), 0 complaints in 3 years. Not a chain/franchise/roll-up: one HQ, family-owned LLC, no parent entity, no franchise language. Website live (HTTP 200, copyright 2026). Inbound channels: phone in header + contact form. No competing AI receptionist vendor found in page source. Suppression list: no match on 'viking' or domain. NOT DONE: GHL 'E4L Services' dedupe via ghl-contacts.js (run before loading). | BN3: D1 Decision-maker: 8/20 - Owners Nicole (Nikki) & Kelly Bridge cited on careers page, BBB principals, ROC-derived BuildZoom record, LLC registered agent; only a generic info@ mailbox (in company JSON-LD) and a staffed main line; no owner email/LinkedIn/direct line -> DEMO PATH, call-first. | D2 Phone/after-hours gap: 15/15 - phone-first ('Call Now: 480-689-5167' header, no booking widget); inherently urgent niche; '24/7 emergency HVAC services' + schema hours 00:00-23:59 daily; no answering service/AI/call center mentioned anywhere (site + source). | D3 Leak evidence: 10/15 - 2 signal types: (2) live dispatcher job post on careers page; (5) no online scheduling + no chat/text + no response-time promise (verified in source). Google reply rate/Yelp not reachable; no complaint quotes found. | D4 AI search gap: 0/10 - NO EVIDENCE (no platform checked; search budget exhausted). FAQPage + HVACBusiness schema present on homepage. | D5 ICP/ability to pay: 15/15 - independent LLC, 1 location, named owners; HVAC core niche; proxies: since 2016 (BBB), 481 reviews with 10 in last 10 days, LinkedIn 11-50 employees, HVAC install ticket + financing offered, 36-city area + 24/7 claim. | D6 Buying signals: 11/15 - paid-media instrumentation (GCLID/UTM/CallRail capture, Meta pixel, GTM) plus live but undated dispatcher post and fall-season push; Sponsored/LSA/Ad Library could not be verified; 2025 PR is >180 days and now 404. | D7 Attitude/stack: 10/15 scale is 10 -> 10/10 - net 4 positives (modern site 2026 + schema; tech adoption: Service Fusion, CallRail, financing, review widget; recent company posts Oct 2026; growth posture: hiring, 'growing across the East Valley', awards/Diamond Contractor); no hostile signals; no named bundled agency or in-house marketer (unnamed content vendor likely). | TOTAL 69/100 = QUALIFIED band; status TRUSTED (6 of 7 dimensions evidenced, D1 positive, D3 direct job-post URL, D5 evidenced; GHL dedupe still required). Not SEND TODAY because the D4 spot-check was not run. | BO3: https://blog.viking-hvac.com/careers, https://www.viking-hvac.com/, https://www.buildzoom.com/contractor/viking-heating-air-conditioning-az, https://www.bbb.org/us/az/chandler/profile/heating-and-air-conditioning/viking-heating-and-air-conditioning-llc-1126-1000075245, https://opencorporates.com/companies/us_az/L20751017, https://www.viking-hvac.com/contact-us/, https://www.viking-hvac.com/about-us/, https://www.linkedin.com/company/viking-heating-and-air-conditioning, https://serviceagent.ai/directory/arizona/chandler/hvac/viking-heating-and-air-conditioning/, https://blog.viking-hvac.com/, https://blog.viking-hvac.com/blog/41-mph-winds-hit-chandler-more-monsoon-storms-coming-this-week, https://www.google.com/maps/search/?api=1&query=Google&query_place_id=ChIJYXSnVIcHK4cRsYunCS6JiyU, https://viking-hvac.com/location-sitemap.xml, https://www.viking-hvac.com/robots.txt, https://adstransparency.google.com/?region=US&domain=viking-hvac.com (no data rendered), https://markets.financialcontent.com/thriventfinancial/article/binary-2025-10-8-viking-hvac-expands-commercial-services-in-phoenix-valley (scout capture 2025-10-08; 404 on 2026-10-12) | BP3: Medium | BQ3: Title detail: Owner / Member (founder per site schema 'Nikki Bridge'; registered agent of the LLC; BBB principal 'Nicole E. Bridge, Owner'). Co-owner: Kelly Bridge, 'HVAC Tech./Owner' (ROC record via BuildZoom; BBB 'Owner'). Legal entity note: legal: Viking Heating and Air Conditioning, LLC. Second decision-maker: Kelly Bridge, 'HVAC Tech./Owner' (likely in the field) - Nicole/Nikki is the registered agent and schema founder, so she is the better first ask; license qualifying party is Joel Montoya (not an owner). Email is generic info@ only - route to Sam first; if emailing, write for a gatekeeper and ask for Nikki or Kelly. Best call window (AZ, no DST, MST): trades 7:00-8:30am or 4:00-5:30pm. Phone 480-689-5167 is consistent across site, BBB and BuildZoom (CallRail present, but this appears to be the main line, not a swapped tracking number). Marketing stack signals an unnamed vendor (CallRail, Meta pixel, automated weather-triggered blog at blog.viking-hvac.com, 8 LinkedIn posts in 10 days) - ask 'who runs your blog and ads?' before pitching GEO; FAQPage schema already on the homepage. Watch-outs: review reply tone unknown (could not render Google replies); 'Best of business rate 2024/2025' badge issuer not identified; the Oct 2025 commercial-expansion PR now 404s (do not cite it as current); a technician named Logan Bridge appears in an Oct 2, 2026 review - do not assume any relation. Before loading to GHL: run ghl-contacts.js dedupe (domain viking-hvac.com / 480-689-5167 / name+Chandler); run the D4 AI spot-check (3 money questions x 2 platforms) to see if this can move to SEND TODAY. Compliance: no cell numbers found; main line is a business line; no 'no solicitation' notice seen.
A4: 20261012-03 | B4: 2026-10-12 | C4: 1 | E4: New | F4: 69 | G4: =IF(F4="","",IF(F4>=80,"A — send today",IF(F4>=60,"B — worth a touch",IF(F4>=40,"C — hold","D — reject")))) | H4: Bob Heinmiller Air Conditioning, Inc. | I4: Mark | J4: Derringer | K4: Owner/President | L4: Not found | M4: None found | N4: Not found | O4: Not found (no owner cell or direct line on site, BBB, Carrier, or reviews; only the main line, fax, and the alternate 407-422-7657 office number) | P4: +1 407-374-0779 (site header 'Hotline', footer, BBB, DispatchCore). Also published: fax +1 407-422-0790; alternate +1 407-422-7657 (contact-page meta description 'Call Us Today' and Experience.com contact number); Carrier dealer page lists +1 321-319-3980 (different number on Carrier's locator - do not assume it reaches the office) | Q4: HVAC (also electrical, generators, solar via sister entity Bob Heinmiller Solar Solutions, LLC) | R4: core | S4: Orlando | T4: FL | U4: Growth posture is public right now: a 2026 Top Solar Contractor award posted July 24, 2026, plus open installer and comfort-advisor roles - more jobs and more calls hitting the same office line. An Aug 11, 2026 public review already shows daytime calls being pushed to callbacks. Florida's cooling season runs through October, and the Google listing appears unclaimed on two directories with no FAQ/LocalBusiness schema on the site, so they are invisible in the AI answers checked while franchise competitors (Aire Serv, One Hour) are named. The site itself was refreshed in April 2026, so they are investing in presence this year. | V4: Family-Legacy Pride Brand (primary); Growth-Minded Operator (secondary). Confidence: high (5+ signals across site, press, BBB, job boards). | W4: Voice AI live demo built from bobheinmiller.com (after-hours and overflow coverage on the hotline, booking into their process), framed as protecting a three-generation name - never as replacing office staff. Secondary ask: the free AI-visibility audit ('named in 0 of 3 so far; full 28-answer run on request'). Route: call-first (Sam) with the demo number; service@ email as backup with gatekeeper-friendly copy. demo_build = yes (D2 >= 9, site scrapable); run_geo_audit = yes (D4 = 6). | X4: Recover | Y4: who picks up at Bob Heinmiller after 5? | Z4: Congrats on the 2026 Top Solar Contractor list - three generations in Orlando and still growing. Curious who picks up your line after 5. | AA4: Family-legacy protection + after-hours/overflow relief. Reference the 1945 roots and the July 2026 award, then the neutral observation that the homepage promises same-day/24-7 but the '24/7 Call Service Support' button lands on a web form and a recent public review describes a morning call deferred to an afternoon callback (summarize as a pattern; never quote the reviewer). Offer: a demo line trained on Bob Heinmiller's own site that answers what already rings out, qualifies the caller (name, number, address, no-cool vs. maintenance, urgency) and books the visit; go-live is one conditional call-forwarding rule, rollback is one dial code; nothing to pay before they hear it. Close with ask #1 (20-minute Game Plan Call with Sebastian) or ask #2 (an email address for the free AI-search audit - note they are not named for Orlando money questions in the checks run so far while AC's Heating & Air, Belle Air, and Aire Serv are). | AB4: 'We already offer 24/7 service and our office handles the phones' / 'We've been here 36 years, referrals are our marketing' (Mark's own words: 'There is no better accolade or recognition than a business referral'). Answer: it only takes the calls that already ring out or get a 'we'll call you back' - referral callers still have to get through; the receptionist is trained on their story so callers still reach 'Bob Heinmiller'; office staff keep every call they answer; conditional forwarding only, no change to the number. Secondary objection: vendor fatigue / 'we have a marketing company' (Orange Rock Media builds the site; E4L is not a web or SEO replacement). | AC4: "Hi, this is Sam with Eat 4 Life Marketing - this is a cold call, so feel free to hang up on me. I'm trying to reach Mark Derringer. The reason I'm calling: your homepage promises same-day, 24/7 service, but the '24/7 Call Service Support' button actually sends people to a web form, and one of your August reviews describes a morning caller being pushed to an afternoon callback. We build an AI receptionist trained on Bob Heinmiller's own site that picks up every call that rings out after hours or when the office is slammed, qualifies the caller, and books the visit - and you can call a demo line we build from your website before you pay anything. Can I take 20 seconds to tell you how it would work for a three-generation shop like yours, and you tell me if it's worth a longer conversation?" | AD4: Tue-Thu 8:00-8:30 AM ET (Florida telemarketing floor is 8 AM; call before trucks roll and before the office queue builds - an Aug 11, 2026 public review says a morning caller was told 'she'd have to call me back this afternoon'). Fallback 4:00-5:00 PM ET when installs wrap. Ask for Mark Derringer (Owner/President) by name; if out, ask for Linda Heinmiller (Owner/Corp. Secretary). A 2023 review says the owner did not return four calls, so expect to book a time rather than get him live. | AE4: Site publishes NO hours anywhere; only 'Same day and 24/7 emergency service available' and 'You can receive same-day care from a qualified expert 24 hours a day throughout the week' (https://www.bobheinmiller.com/). Google data mirrored by DispatchCore and YellowPages: 'Open 24 hours' Monday-Sunday (listing unclaimed). Sister entity Bob Heinmiller Solar Solutions (1519 W Smith St, same owners) lists Mon-Fri 8:00 AM-5:00 PM, closed Sat-Sun (Birdeye, TrustAnalytica). serviceagent.ai (Google data): 'After-hours and emergency response isn't signaled on the public profile.' | AF4: America/New_York (Eastern) | AG4: Main line +1 407-374-0779 is answered by office staff, not the owner: Aug 11, 2026 review - 'I call for ac service this morning and the young lady said she'd have to call me back this afternoon' (https://www.solarreviews.com/installers/bob-heinmiller-solar-solutions,-llc.-reviews); a Jan 19, 2023 review on the solar entity names an office staffer 'Ashley' promising a callback 'within the hour' (STALE, role not stated). No office manager or dispatcher named on the site or in reviews; 'Meet Our Staff' lists only Bob Heinmiller (Founder), Linda Heinmiller (Owner/Corp. Secretary), Mark Derringer (Owner/President). Field names in reviews: techs Tyler, Chris; comfort advisor/sales Patrick Liner; installers Michael, Anthony. No answering service, call center, or AI receptionist vendor in page source. No owner cell published. Employment page lists 'Administrative' as an application category (no confirmed opening). Get through by asking for 'Mark Derringer' or 'Linda' by name and offering to book a 20-minute slot rather than pitching the person who answers. | AH4: The July 24, 2026 blog post 'Bob Heinmiller Solar Solutions named a 2026 Top Solar Contractor' (https://www.bobheinmiller.com/blog/) - a dated win within 90 days, safe to congratulate, and it pairs with the three-generation story. Then pivot to the neutral phone-process observation (site promises 24/7; the '24/7 Call Service Support' button goes to a web form). | AI4: (1) Aug 11, 2026 review (Pearl Ings, SolarReviews page for the sister entity, but about AC service): 'I call for ac service this morning and the young lady said she'd have to call me back this afternoon.' - https://www.solarreviews.com/installers/bob-heinmiller-solar-solutions,-llc.-reviews (2) Jan 19, 2023 review (Pam Kilgore, same page; also on TrustAnalytica): 'I have placed 4 calls to Mark, the owner, who will not call me back.' - older than 18 months, context is a $225 generator service-charge dispute; reviewer says staff promised callbacks 'within the hour' and 'that day' that did not happen. (3) 24/7 claim with no published hours and the '24/7 Call Service Support' CTA routing to a web form (https://www.bobheinmiller.com/). (4) No online booking, chat, or text widget (page source). (5) No owner replies on any review mirror; Google listing shown as 'unclaimed' on two directories. (6) BBB: 2 complaints in 3 years, one 2026 complaint unresolved. Strongest signal for the opener: item (1). | AJ4: Award/press: 'Bob Heinmiller Solar Solutions named a 2026 Top Solar Contractor' blog post dated July 24, 2026 (81 days old) - https://www.bobheinmiller.com/blog/ ; Solar Power World 2026 list #330 - https://www.solarpowerworldonline.com/suppliers/bob-heinmiller-solar/. Hiring: Home Comfort Advisor (sales) on CareerBuilder 'POSTED 30+ days ago', undated - https://www.careerbuilder.com/job-details/home-comfort-advisor-orlando-fl--a83cea90-709a-4504-bc87-28a433854c52 ; Entry Level HVAC Installer in Talent.com feeds (undated). Site refresh: contact page dateModified 2026-04-09; homepage © 2026. Seasonal: no Orlando-specific heat or storm event found in the last 60 days (searched); Florida AC season runs through October (typical highs ~84F). No front-office (CSR/dispatcher/receptionist) job post found. | AK4: Family-Legacy: 'For over 60 years my family has been helping families just like yours'; 'three generations later'; 'We are family owned and operated' (https://www.bobheinmiller.com/about-us/); homepage image alt 'Bob Heinmiller Derringer Family Owned and Operated'; surname in the business name; BBB Accredited since 8/15/1991 (https://www.bbb.org/us/fl/orlando/profile/air-conditioning-contractor/bob-heinmiller-air-conditioning-inc-0733-101349); Mark: 'There is no better accolade or recognition than a business referral' (2019 release). Growth-Minded: OBJ Fast 50 (2019), Top Solar Contractor 2025 and 2026 (blog), hiring Entry Level HVAC Installer (Talent.com feed) and Home Comfort Advisor (CareerBuilder, 30+ days), 0% / 24-month financing offer, GTM + Meta pixel on site, agency-built site (Orange Rock Media, © 2026). Caution signal toward Overwhelmed/Absentee: no owner replies on any review mirror and a Jan 2023 review 'I have placed 4 calls to Mark, the owner, who will not call me back' (solar entity, older than 18 months, half weight). | AL4: Third-generation family HVAC business: 'My grandfather, Ben Heinmiller started his air conditioning business in Orlando in 1945. My father, following in his footsteps, opened Bob Heinmiller Air Conditioning in 1990' - Linda Heinmiller-Derringer, https://www.bobheinmiller.com/about-us/. Mark Derringer is Owner/President; the company's 2019 release quotes him on growth and referrals and on the company's free energy checkup. Company awards: Orlando Business Journal '50 fastest growing companies in Central Florida' (2016-2018 growth, release dated June 21, 2019), Carrier 2018 President's Award, Solar Power World Top Solar Contractor 2025 and 2026 (#330 overall, 1,275 kW installed in 2025). BBB A+ accredited since 1991. Blog carries a tribute to an 11-year employee (Kenny Haslacker), signaling long-tenure culture. No podcast, interview, military, or trade-school facts published. | AM4: Tone: warm_personal, family-legacy, professional. Verbatim: Mark Derringer - 'There is no better accolade or recognition than a business referral' and 'we empathize with families who work hard for their money and become understandably frustrated with their costly power bills' (https://www.bobheinmiller.com/about-us/one-of-50-fastest-growing-companies-in-central-florida/). Linda Heinmiller-Derringer - 'For decades, our family has set a standard of being the most knowledgeable in our industry' (same page); 'Heating, cooling, and electrical solutions, from our family to yours' and 'if you need service today, we're just a phone call away' (https://www.bobheinmiller.com/about-us/). Bragging points: three generations since 1945, Carrier Factory Authorized + President's Award, NATE-certified background-checked uniformed techs, 100% satisfaction guarantee, flat-rate pricing, A+ BBB since 1991. Community: a 'Scholarship' page is linked in the footer. Review-reply behavior: none observed on any mirror. | AN4: Owner-operator | AO4: Not found (Google X-ray for Mark Derringer and Linda Heinmiller-Derringer returned no linkedin.com/in profile; only a RocketReach aggregator stub exists, which is not a usable source). Company page: https://www.linkedin.com/company/bob-heinmiller-air-conditioning-inc/ | AP4: No personal owner accounts found. Company accounts linked from the site: Facebook https://www.facebook.com/bobheinmiller/ (login-walled, not readable), Instagram https://www.instagram.com/bobheinmillerac/ (not readable), X https://x.com/BobHeinmiller, YouTube https://www.youtube.com/@BobHeinmillerAir (2 videos), LinkedIn company page (88 followers). Social recency could not be observed. | AQ4: https://www.bobheinmiller.com | AR4: service@bobheinmiller.com (site footer, Contact Us and About pages - https://www.bobheinmiller.com/contact-us/). Searches for '@bobheinmiller.com' off-site returned no personal addresses. MX lookup not available in this environment. | AS4: 1537 W. Smith Street, Orlando, FL 32804 (site footer; contact-page body has a typo '137 W.Smith St.'; BBB and Carrier dealer page agree on 1537) | AT4: 32804 | AU4: Orlando plus 24 other named communities on the homepage: College Park, Central Florida, Winter Park, Maitland, Casselberry, Apopka, Altamonte Springs, Longwood, Oviedo, Winter Springs, East Orlando, Windermere, Dr. Phillips, Winter Garden, Sanford, Lake Mary, Heathrow, Pine Castle, Conway, Union Park, Kissimmee, St. Cloud, Hunters Creek, Mount Dora (https://www.bobheinmiller.com/) | AV4: Not found (Google Business Profile could not be opened from this environment; Google data mirrored at https://www.dispatchcore.io/directory/hvac/orlando-fl/bob-heinmiller-air-conditioning-inc and https://serviceagent.ai/directory/florida/orlando/32804/hvac/ - both mark the listing 'unclaimed') | AW4: 4.7 per DispatchCore (450 reviews) and serviceagent.ai (463 Google reviews); ~4.5 per Carrier dealer page (592 Google reviews); 4.52 per Experience.com (323). Counts differ by capture date. | AX4: 450-592 Google (DispatchCore 450; serviceagent.ai 463; Carrier dealer page 592); Yelp page title shows 32 reviews (page blocked, 403); BBB 3 reviews / 2 complaints in 3 years | AY4: 1990 (site About: 'My father... opened Bob Heinmiller Air Conditioning in 1990'; BBB foundingDate 1990-04-01; BBB Accredited since 8/15/1991; Experience.com 'Year Started: 1990'). Family roots: 'My grandfather, Ben Heinmiller started his air conditioning business in Orlando in 1945.' Solar line 'over 15 years' per July 2026 blog post. Licenses: CAC057411 (A/C), CVC56861 (solar), EC0001898 (electrical) per site footer. | AZ4: LinkedIn company page: '11-50 employees' (12 listed on LinkedIn, 88 followers) - https://www.linkedin.com/company/bob-heinmiller-air-conditioning-inc/; Solar Power World supplier listing: 42 employees - https://www.solarpowerworldonline.com/suppliers/bob-heinmiller-solar/; at least 5 field staff named in 2025 reviews (Tyler, Chris, Patrick, Michael, Anthony) | BA4: 1 (1537 W Smith St). Sister entity Bob Heinmiller Solar Solutions, LLC at 1519 W Smith St on the same block (Yelp/EnergySage/Birdeye) - same family, not a second HVAC location. | BB4: Residential and commercial AC repair and installation (Carrier Factory Authorized Dealer; Carrier President's Award winner per Carrier dealer page - year not stated on source), electrical contracting and electrical preventative maintenance, Generac standby generators, EcoFlow home solutions, indoor air quality, solar power (via Bob Heinmiller Solar Solutions), trenchless drilling, warranty program, 0% interest / no payments for 24 months financing via third-party lender (site menu + financing page) | BC4: basic (AC site: SSL, WordPress/Astra, Fluent Forms contact form, GTM + Meta pixel, financing; no booking, chat, or text widget) with one modern element on the solar sister entity (Birdeye review page, 116 reviews - https://reviews.birdeye.com/bob-heinmiller-solar-solutions-orlando-solar-contractor-156234086765216) | BD4: agency_managed (footer 'Design and Marketing by Orange Rock Media'; GTM + Meta pixel id 228471372387891; PRWeb/PRNewswire-style award releases on the blog; WP Rocket, Yoast-style Organization schema). No bundled vertical agency (Scorpion/Hibu/Thryv) and no in-house marketer found. | BE4: established (36 years, 450-592 Google reviews, 11-50 employees, hiring field and sales roles, 2026 award) | BF4: none observed - zero owner replies on Experience.com (323 Google-mirrored reviews), Birdeye (solar), TrustAnalytica, and SolarReviews; Google Business Profile itself could not be opened, so GBP reply rate is unverified. The one 2026 BBB complaint drew a company response that 'denies responsibility' and cites an 'existing condition' (dispute unresolved) - a denial, not hostile. | BG4: claims_24_7, coverage unverified. Site: 'Same day and 24/7 emergency service available' and '24/7 Call Service Support' (button links to /contact-us/ web form, not a phone line). Google data via unclaimed mirrors: 'Open 24 hours' Mon-Sun. No answering-service, call-center, or AI-receptionist vendor in page source. Sister solar entity lists Mon-Fri 8-5 only. Aug 11, 2026 review shows daytime calls being deferred to callbacks. Sam should record who answers on the first dial. | BH4: None. 'Get a Quote' / 'Immediate Service Request' / '24/7 Call Service Support' all route to the Contact Us form (Fluent Forms; fields Name/Email/Phone/Type of Service; no response-time promise). Page-source scan found no calendly, acuity, housecallpro, servicetitan, jobber, or scheduler scripts; the words 'schedule' on the page are plain copy. | BI4: None. No podium, birdeye, tidio, intercom, drift, tawk, livechat, textline, or weave scripts in the homepage source; no 'text us' link. | BJ4: WordPress (Astra theme, WP Rocket 3.23.5.1, Beaver Builder/UABB modules, Fluent Forms), Google Tag Manager + gtag, Meta Pixel (fbq id 228471372387891), Organization/WebSite/WebPage/BreadcrumbList JSON-LD (no LocalBusiness or FAQPage), agency credit Orange Rock Media; Birdeye on the solar sister entity; third-party consumer financing (lender not named); Carrier dealer locator; BBB seal. No call tracking (callrail/CTM) detected; robots.txt has no AI-crawler blocks. | BK4: Not verified. Google Ads Transparency Center and Meta Ad Library could not be loaded from this environment (Meta returned 403; Google not checkable); no Google Guaranteed / LSA badge seen by the scout; the site carries GTM and a Meta pixel, so paid-social measurement is in place. Log as null for groups (a), (b), (c). | BL4: Named in 0 of 3 AI answers (platform: Claude web-search answer only; ChatGPT, Perplexity, and Gemini could not be reached from this environment - Perplexity returned 403). Questions: 'emergency AC repair near Orlando FL', 'most reliable HVAC company in Orlando FL', 'HVAC company that answers the phone Orlando FL'. Competitors named: AC's Heating & Air, Aire Serv, Smart Home Air & Heat, Quick Air USA, Downtown Air and Heat, Belle Air, ServiceOne, Clear Comfort, Gary Munson, Certified Climate Control, One Hour Heating & Air, Pure Air and Heating, Mechanical One. Site has no FAQPage or LocalBusiness schema. A full 28-answer E4L audit is still required before quoting a count to the prospect. | BM4: PASS. Chain/franchise/PE: no - independent family corporation ('Family Owned and Operated', three generations), 1 location, no parent entity found. Website: working own-domain WordPress site (HTTP 200, SSL, © 2026, modified 2026-04-09). Live U.S. business: Orlando FL, BBB A+ accredited since 1991, hiring, July 2026 award, 2025-2026 reviews. Inbound channel: hotline + contact form. Not a competitor/non-buyer. Not already automated: no AI receptionist, answering service, or GEO vendor in page source; named in 0 of 3 AI answers. Not in E4L's world: grep of suppression.csv and seen.csv for 'heinmiller' / 'bobheinmiller' = 0 hits; not in geo/clients.json, geo/audits/, or demos/; no 'no solicitation' notice found. NOT RUN: GHL 'E4L Services' sub-account dedupe (ghl-contacts.js). Flag: directory lists CAC057411 expiring 08/31/2026 and DBPR returned no record for my query - verify before citing. | BN4: D1 Decision-maker: 8/20 - Mark Derringer, Owner/President, cited on the site 'Meet Our Staff' page and BBB Business Management (two sources); co-owner Linda Heinmiller, Owner/Corp. Secretary; only a generic mailbox (service@bobheinmiller.com); no LinkedIn, no direct line -> call-first route. | D2 Phone/after-hours gap: 9/15 - phone-first ('Hotline' in header, 'Call for fast, friendly service'), 24/7 claim on site, Google-mirrored hours 'Open 24 hours' (unclaimed listing), no answering-service or AI vendor in source, '24/7 Call Service Support' button goes to a web form; no direct proof of who answers after hours, so not 15. | D3 Lead-response leak: 10/15 - two distinct signal types: (1) verbatim responsiveness review dated Aug 11, 2026 plus an older Jan 19, 2023 'will not call me back' review; (5) no booking, chat, or text widget verified in page source and the contact form has no response-time promise. Signal (3) owner-reply neglect is probable (zero replies on four mirrors) but GBP itself was not opened, so not counted. | D4 AI search gap: 6/10 - Named in 0 of 3 answers on one platform (min 3 answers met), competitors named, no FAQPage/LocalBusiness schema; other platforms unreachable. | D5 ICP fit / ability to pay: 15/15 - independently owned family corp, 1 location, named owners; HVAC core niche; 5+ proxies: since 1990 (BBB foundingDate, accredited 1991), 450-592 Google reviews, LinkedIn 11-50 / SPW 42 employees with 5 named field staff, HVAC install ticket $6-12k plus 0%/24-month financing, 24-community service area and 24/7 claim. | D6 Buying signals: 11/15 - dated trigger 61-180 days (2026 Top Solar Contractor post, July 24, 2026) plus spend groups (d) GTM + Meta pixel + agency credit and (e) Birdeye on the solar entity; sales + installer job posts (undated); groups (a)(b)(c) not checkable from here - logged null. | D7 Attitude / stack: 10/10 - positives: modern site (© 2026, modified 2026-04-09, SSL), tech adoption (financing, Meta pixel, Birdeye on solar), growth posture (2026 award, hiring, OBJ Fast 50, Carrier President's Award); no hostile replies, no anti-marketing statements, no bundled vertical agency (Orange Rock Media is a local web shop). TOTAL 69/100 -> QUALIFIED band (55-74). Status: TRUSTED on the checks run here (7/7 dimensions with evidence, D1 positive citation, D3 verbatim, D5 cited); GHL 'E4L Services' dedupe via ghl-contacts.js was NOT run from this subagent - orchestrator must run it before load. | BO4: https://www.bobheinmiller.com/about-us/meet-our-staff/, https://www.bbb.org/us/fl/orlando/profile/air-conditioning-contractor/bob-heinmiller-air-conditioning-inc-0733-101349, https://www.bobheinmiller.com/, https://www.bobheinmiller.com/about-us/, https://www.bobheinmiller.com/contact-us/, https://www.solarreviews.com/installers/bob-heinmiller-solar-solutions,-llc.-reviews, https://trustanalytica.org/us/fl/orlando/reviews/bob-heinmiller-solar-solutions, https://www.bobheinmiller.com/blog/, https://www.bobheinmiller.com/about-us/one-of-50-fastest-growing-companies-in-central-florida/, https://www.solarpowerworldonline.com/suppliers/bob-heinmiller-solar/, https://www.dispatchcore.io/directory/hvac/orlando-fl/bob-heinmiller-air-conditioning-inc, https://serviceagent.ai/directory/florida/orlando/32804/hvac/, https://www.experience.com/reviews/bob-22278495, https://www.carrier.com/us/en/residential/dealers/fl/orlando/1537-w-smith-st-3482-loc, https://www.linkedin.com/company/bob-heinmiller-air-conditioning-inc/, https://www.careerbuilder.com/job-details/home-comfort-advisor-orlando-fl--a83cea90-709a-4504-bc87-28a433854c52, https://reviews.birdeye.com/bob-heinmiller-solar-solutions-orlando-solar-contractor-156234086765216, https://www.bobheinmiller.com/about-us/employment-opportunities/, https://energysage.com/supplier/27822/bob-heinmiller-air-conditioning-inc, https://www.yelp.com/biz/bob-heinmiller-air-conditioning-orlando-7, http://web.archive.org/web/20231224213759/https://bobheinmiller.com/ | BP4: Medium | BQ4: Title detail: Owner/President (site 'Meet Our Staff' page: 'Mark Derringer Owner/President'; BBB Business Management: 'Mark Derringer, President'; quoted as 'Mark Derringer, President of Bob Heinmiller Air Conditioning' in the company's June 21, 2019 release). Co-owner: Linda Heinmiller(-Derringer), 'Owner/Corp. Secretary' on the site, 'Linda Derringer, Secretary' on BBB; she signs the About-Us letter and is the family-legacy voice. Founder: Bob Heinmiller.. 1) Address Mark Derringer as Owner/President; Linda Heinmiller(-Derringer), Owner/Corp. Secretary, signs the family letter - consider copying her on email; do not characterize their relationship beyond 'co-owners'. 2) Only a generic mailbox exists (service@) - route call-first; if emailing, write for a gatekeeper and ask for Mark by name. 3) Never quote the 'will not call me back' or 'call me back this afternoon' reviews verbatim to the owner; summarize as a pattern. 4) Do not imply replacing office staff - position as after-hours/overflow only (Family-Legacy playbook). 5) Not verified from here: GBP hours and owner-reply rate (Google blocked), Google Ads / Meta Ad Library / LSA (blocked), ChatGPT/Perplexity/Gemini spot-check (blocked - only one platform checked). 6) A directory shows license CAC057411 'exp 08/31/2026'; DBPR search returned no record for my query - verify renewal on myfloridalicense.com before citing the license. 7) Sister entity Bob Heinmiller Solar Solutions, LLC (1519 W Smith St, Birdeye-managed reviews, Mon-Fri 8-5) shares the owners - one demo line could cover AC + electrical + solar intake. 8) Carrier's dealer page shows a different phone (321-319-3980) - they may already have a dealer-locator tracking line; ask, don't assume. 9) Suppression.csv and seen.csv are clean; GHL E4L Services dedupe (ghl-contacts.js) still needs to run before load. 10) Florida call window is 8 AM-8 PM; Sam should log who answers (human/IVR/voicemail) to update D2.
A5: 20261012-04 | B5: 2026-10-12 | C5: 1 | E5: New | F5: 68 | G5: =IF(F5="","",IF(F5>=80,"A — send today",IF(F5>=60,"B — worth a touch",IF(F5>=40,"C — hold","D — reject")))) | H5: Appalachian Tree Service of Atlanta, Inc. | I5: Ryan | J5: Strache | K5: President/Owner | L5: ryan@appalachiantreeservice.com | M5: Personal (named) | N5: Confirmed | O5: Not found (only the main line +1 404-409-9926 is published on site, BBB and Nextdoor; line type not stated, do not text) | P5: +1 404-409-9926 | Q5: Tree service (climber-led tree removal, trimming/pruning, debris hauling, undergrowth clearing, storm-damage cleanup) | R5: extend | S5: Kennesaw | T5: GA | U5: A dated promotion is live through Oct 31, 2026 ('Save 10% This October' on hazard trees and referrals), fall storm/leaf-drop season is on, the site was just relaunched (July 2026) and is still being added to (HVAC partner page Sept 12, 2026), and Affirm financing is being set up for larger jobs — every one of those pushes inbound calls into a Mon–Fri 9–5 window with 'no nighttime dispatch'. The owner is clearly investing in his web presence this quarter; the after-hours phone is the piece that is still uncovered. | V5: Growth-Minded Operator (medium confidence: 4 signals across 2 source categories - website + third-party profiles); secondary: Overwhelmed Owner-Operator | W5: Voice AI live demo built from appalachiantreeservice.com (generic home-services template: trade = tree service; scenario = tree down on the house after a storm at 9 PM; the AI qualifies the caller, captures address/damage details and books the first-morning assessment - no nighttime dispatch promised) + missed-call text-back. demo_build = yes (phone-first, D2 = 15, site scrapes cleanly). run_geo_audit = after D4 spot-check. | X5: Recover | Y5: Who takes the 9 PM storm call in Kennesaw? | Z5: Ryan, your storm-damage pages say it plainly: 'There is no after-hours nighttime dispatch' — fair enough for a climber-led crew, but the homeowner with a limb on the roof at 9 PM usually just calls the next Kennesaw tree service on Google. | AA5: Relief + coverage, not growth: he is the climber, the estimator and the inbox, and he is paying to drive calls right now (October 10%-off hazard-tree promo, brand-new site, 48 storm-damage city pages added Sept 1) while evening calls go to voicemail. Pitch the storm-week scenario: an AI receptionist trained on his own site answers the after-hours and overflow calls, qualifies the caller (name, address, what fell, photos via the form link), and books the morning assessment — it never dispatches at night, it just keeps the lead. Proof lever: 'we already built a demo line from your website; call it before you pay a dollar.' Go-live = one conditional call-forwarding rule for missed/busy calls; rollback is one dial code. Ask #1: 20-minute Game Plan Call. Ask #2: the free AI visibility check once D4 runs. Keep it to 3 short lines; do not say he misses calls (reviews praise his response speed) and do NOT say weekends are uncovered (his storm pages accept weekend urgent calls) — say 'after 5 PM' / 'overnight'. | AB5: 'I'm a small climber-led crew and I don't do night work — I don't need more calls I can't handle.' Answer: the receptionist does not dispatch anything; it answers, captures the details and books the assessment into the next open morning so you choose the jobs instead of losing them to whoever picked up. Secondary: 'I just rebuilt the site / I handle the phone myself' — it only covers the calls that already go to voicemail, trained on that new site, nothing for you to set up beyond one forwarding rule. Budget sensitivity is likely (solo email, no office staff) — keep pricing for the Game Plan Call. | AC5: Hi Ryan, this is Sam with Eat 4 Life Marketing — this is a cold call, so feel free to hang up on me. I was on your site this week: nice October hazard-tree special. I also noticed your storm-damage pages say there's no after-hours nighttime dispatch — which makes sense when you're the one in the tree. We build an AI receptionist trained on your own company that picks up the 9 PM storm call, gets the address and what came down, and books your first morning assessment — and we build the demo line from your website before you pay anything. Can I take 20 seconds to tell you how it works, or is this a bad time? | AD5: Tue–Thu 4:15–5:00 PM ET — the last 45 minutes of his posted Mon–Fri 9–5 window, when a climber-led crew is off the tree and the site says requests are reviewed 'during our stated operating hours'; fallback Mon–Fri 9:00–9:30 AM ET right at opening before the crew rolls. Do not call outside 9–5 ET (closed; voicemail only). | AE5: Mon–Fri 9:00 AM–5:00 PM; Sat–Sun Closed for normal operations (contact page, JSON-LD OpeningHoursSpecification, Nextdoor). EXCEPTION on the 48 /storm-damage/{city} pages: 'Weekend calls are accepted for urgent storm inquiries and estimates. No after-hours nighttime dispatch.' Google Business Profile not opened directly. | AF5: America/New_York (Eastern Time) | AG5: No office manager, dispatcher or answering service is named anywhere (site, BBB, Nextdoor; no vendor scripts in source). The only mailbox is ryan@, and a Nextdoor reviewer refers to 'Ryan and his staff', so the main line +1 404-409-9926 most likely rings to Ryan or straight to voicemail during a job. Ask for Ryan by first name; if a crew member answers, ask when Ryan reviews estimate requests (site says during 9–5) and call back then. Line type not published — manual dial only, no SMS. If voicemail: leave name, 'built a demo line for Appalachian Tree Service', and let Sebastian's email carry it. | AH5: The live October promotion: 'October Special • Active Oct 1 – Oct 31 — Don't Let Spooky Trees Haunt Your Home — Save 10% This October' on the newly relaunched site (https://www.appalachiantreeservice.com/, seen 2026-10-13). Dated, positive, business-specific and his own words; pairs naturally with 'every call that promo brings in after 5 PM currently waits until morning' (contact page: 'We review requests during our stated operating hours'). | AI5: (a) Storm calls after 5 PM have nowhere to go: homepage Service schema 'Storm-damage inquiries, assessment and cleanup ... during listed inquiry hours; no nighttime dispatch'; /storm-damage/{city} pages: 'There is no after-hours nighttime dispatch.' (b) Contact page: 'We review requests during our stated operating hours.' (c) Owner is the crew: 'Our experienced climber works with ropes and safety gear' (singular) on /about; the only published mailbox is ryan@. (d) Booking friction: no scheduler, no chat/text, form with no response-time promise, phone-first CTA 'Call for Free Estimate'. (e) He is spending to drive calls right now (Oct 1–31 10%-off promo, new site, 48 storm-damage city pages added 2026-09-01, 48 blog posts 2026-09-13) while evenings are uncovered. CAUTION: the storm pages say weekend calls ARE accepted for urgent storm inquiries — do not say weekends are uncovered. No reachability complaints found; Nextdoor praises 'quick on a response' — frame as after-5-PM/storm-surge coverage, not missed calls. | AJ5: (1) Dated promotion live now: 'October Special • Active Oct 1 – Oct 31' 'Don't Let Spooky Trees Haunt Your Home — Save 10% This October' (homepage, /contact?promotion=spooky-trees-october-2026) - within 60 days. (2) Bulk content push 2026-09-01: 48 /storm-damage/{city} pages + 24 /tree-removal-permits/{city} pages (sitemap lastmod) - 42 days ago; 48 city blog posts lastmod 2026-09-13 - 30 days ago; /hvac partner page 2026-09-12 - 31 days ago. (3) Website relaunch ~2026-07-16/17 (core pages lastmod 2026-07-17; service-area pages 2026-07-18) - 88 days ago. (4) Affirm consumer financing being set up (financing page). Negatives: none (no closing/selling/retiring signals). Not checkable: job posts (Indeed 403, /careers 404), press, LinkedIn (search budget exhausted). | AK5: (1) Website rebuilt/relaunched ~2026-07-16/17 with 24 new service-area pages (sitemap lastmod 2026-07-18), 20 city blog posts (2026-07-20), LocalBusiness + Service JSON-LD, © 2026 - https://www.appalachiantreeservice.com/sitemap.xml ; RDAP 'last changed 2026-07-16'. (2) Active dated promotion on homepage: 'October Special • Active Oct 1 – Oct 31 ... Save 10% This October ... Available for qualifying active open estimates, new October estimates, and family, friend or neighbor referrals' - https://www.appalachiantreeservice.com/ (2026-10-13). (3) Financing page: 'We're in the process of setting up Affirm financing to give you the option to split larger tree jobs into manageable monthly payments' - https://www.appalachiantreeservice.com/financing. (4) Chases reviews/reputation across platforms: 'Review Us On Google Yelp Facebook Instagram Nextdoor Angi HomeAdvisor Bing Apple Maps BBB Yellow Pages' footer; BBB accredited since 2021-09-08, A+ - https://www.bbb.org/us/ga/kennesaw/profile/tree-service/appalachian-tree-service-of-atlanta-inc-0443-27222938 ; Nextdoor Neighborhood Fave 2022. (5) Added HVAC referral-partner page 2026-09-12 (sitemap). Overwhelmed overlay: 'Our experienced climber' (singular), owner's first-name email is the only mailbox, Mon–Fri 9–5 only, 'We review requests during our stated operating hours'. No negatives found (no hostile replies, no anti-marketing or anti-AI statements; social/GBP replies not accessible this session). | AL5: Not found beyond public business records: President/Owner and registered agent of Appalachian Tree Service of Atlanta, Inc. (GA Domestic Profit Corp, Active/Compliance), business founded 2006-06-30 per BBB, BBB accredited since 2021-09-08 with A+ and 0 complaints in 3 years. No bio, LinkedIn, interview or press found. | AM5: Tone: professional, understated, property-respect and honesty framed; no hype. Verbatim site lines: 'Climber-led tree care for homeowners who care about their property.' / 'We climb it, cut it, carry it out by hand, and haul it away in our dump trailer.' / 'Tell us what's going on with your trees. We'll give you an honest assessment and a free estimate.' / 'provide an honest, no-pressure quote' (tree-removal page). Partner page voice: 'Just like Appalachian Tree Service, Top Tech Mechanical is a local company that takes care of its customers... we use them ourselves.' Reputation-conscious: BBB accredited A+, 'Rated 5.0 on Google · 136 reviews' badge, Nextdoor Neighborhood Fave 2022. Nextdoor reviewer: 'Ryan and his staff were courteous, professional, and easy to work with.' Payment flexibility (Venmo/Zelle/CashApp/PayPal; Affirm 'in the process of setting up'). Site built on an AI website platform (Manus assets/analytics) - comfortable using AI tools, but no 'AI' statements anywhere. | AN5: Owner-operator | AO5: Not found (linkedin.com returned HTTP 429; web-search budget was exhausted this turn so no X-ray was possible) | AP5: Business accounts only (linked from site footer): https://www.facebook.com/AppalachianTree (login wall), https://www.instagram.com/appalachian_tree_service/ (429), https://x.com/appalachian_of (403), https://nextdoor.com/pages/appalachian-tree-service-kennesaw-ga-1/ (Neighborhood Fave 2022), https://www.yelp.com/biz/appalachian-tree-service-kennesaw-2 (403). No personal owner handle found. | AQ5: https://www.appalachiantreeservice.com | AR5: Not found (the only published address is ryan@appalachiantreeservice.com) | AS5: 3070 N Main St NW, Kennesaw, GA 30144-2756 (site footer + BBB + GA SOS record via OpenCorporates) | AT5: 30144 | AU5: Kennesaw HQ; 24 listed cities across Cobb, Cherokee, Fulton, DeKalb, Forsyth, Paulding, Bartow (+Douglas via Austell): Kennesaw, Acworth, Marietta, Smyrna, Woodstock, Canton, Dallas, Powder Springs, Roswell, Alpharetta, Sandy Springs, Buckhead, Brookhaven, Dunwoody, Milton, Cumming, Hiram, Holly Springs, Ball Ground, Austell, Vinings, Cartersville, Emerson, White (https://www.appalachiantreeservice.com/about/ + LocalBusiness areaServed schema) | AV5: https://g.page/appalachian-tree-service (site 'Review Us On Google' link; GBP not opened directly this session) ; footer map link: https://maps.google.com/?q=3070+N+Main+St+Kennesaw+GA+30144 | AW5: 5.0 (site badge 'Rated 5.0 on Google · 136 reviews', aria-label 'Rated 5.0 on Google from 136 reviews. Opens the verified Google p...' on https://www.appalachiantreeservice.com/ as of 2026-10-13; GBP itself not opened) | AX5: 136 Google (per site badge, 2026-10-13); BBB 8 customer reviews, 0 complaints in 3 yrs; Nextdoor 4 recommendations shown; carousel review on site dated 'a month ago' | AY5: 2006 (~20 years): site 'Serving metro Atlanta since 2006'; BBB foundingDate 2006-06-30; domain appalachiantreeservice.com registered 2006-02-05 (RDAP, GoDaddy). GA Domestic Profit Corporation #0651574, status Active/Compliance (OpenCorporates; incorporation date behind login) | AZ5: Not published. Small owner-led crew: About page 'Our experienced climber works with ropes and safety gear' (singular), gallery alt 'Crew posing in front of completed job', Nextdoor reviewer 'Ryan and his staff'; BBB employee count not listed; equipment = climbing gear + dump trailer, no bucket truck/crane mentioned | BA5: 1 (single address on site, BBB, GA SOS/OpenCorporates; 24 service-area pages are cities served, not branches) | BB5: Tree removal; tree trimming & pruning (ANSI A300); debris hauling (hand-carried, dump trailer); undergrowth clearing; 'Storm-Damage Tree Service' (schema: inquiries/assessment/cleanup 'during listed inquiry hours; no nighttime dispatch'); referral-partner pages for stump grinding, landscaping, arborist consultations, roofing, HVAC (Top Tech Mechanical, page updated 2026-09-12) | BC5: modern (borderline advanced): SSL, LocalBusiness + Service JSON-LD schema, AI-built site (Manus), digital payments (PayPal/Venmo/Zelle/CashApp), Affirm financing in setup; BUT no online booking, no chat, no text-us, no GBP messaging evidence, no CRM/call-tracking scripts | BD5: diy (no agency credit; AI-builder site with programmatic city pages/blog; owner-run promo banner; directory listings on Angi/HomeAdvisor/Yelp/Nextdoor; no pixels, GTM or call tracking in source; ads status not checkable this turn) | BE5: established (since 2006, 136 Google reviews at 5.0 per site badge, 1 location) with fresh investment signals (new site Jul 2026, Oct 2026 promo, financing) - leaning 'scaling' on web presence, no hiring evidence found | BF5: unknown (Google Business Profile, Yelp, Angi and HomeAdvisor could not be opened this session - 403/redirect; BBB shows 8 reviews but text not rendered; Nextdoor shows 4 recommendations, no owner replies visible) | BG5: No nighttime coverage claimed. Homepage Service JSON-LD: 'Storm-damage inquiries, assessment and cleanup ... during listed inquiry hours; no nighttime dispatch'. /storm-damage/kennesaw (and 47 sibling city pages, 2026-09-01): 'Storm inquiry hours Monday–Friday: 9:00 AM–5:00 PM for normal operations and dispatch. Saturday–Sunday: Weekend calls accepted for urgent storm inquiries and estimates. There is no after-hours nighttime dispatch.' Contact page: 'We review requests during our stated operating hours.' No 24/7 claim, answering service, AI receptionist or IVR vendor in page source. Gap to pitch = evenings/nights (after 5 PM), NOT weekends. | BH5: None - 'Schedule Free Estimate' and 'Request Online Estimate' buttons go to the /contact form (First/Last name, address, email, phone, 'How Did You Hear About Us?', up to 4 photos, 'Tell Us About Your Trees'); no scheduler script (checked page source: only files.manuscdn.com and manus-analytics.com) | BI5: None - no chat, text-us or messaging widget in page source; form page states 'Your request is not confirmed until the site reports that it was saved.' with no response-time promise | BJ5: Site built/hosted via Manus AI website builder (assets at files.manuscdn.com, /manus-storage/ image paths, manus-analytics.com script); domain registrar GoDaddy (RDAP); email on Google Workspace (MX aspmx.l.google.com - MX present yes); Affirm financing 'in the process of setting up'; payment: PayPal, Venmo, Zelle, CashApp, cards; directory profiles: Angi (companylist ...2847650), HomeAdvisor (rated.AppalachianTreeService.67089025), Yelp, Nextdoor, BBB, Bing Places, Apple Maps, Yellow Pages. NOT found: booking, chat, text, CallRail/CTM, GTM, Meta pixel, Hotjar, CRM forms, agency credit, answering service, AI receptionist. | BK5: Not checked - Google Ads Transparency Center rendered no results for the domain (JS app), Meta Ad Library returned HTTP 403, and the Google 'Sponsored'/LSA checks could not run (web-search budget exhausted this turn). Page source shows no GTM, Meta pixel, gclid/UTM landing pages or call-tracking swap, which usually accompany paid search. HomeAdvisor/Angi pro profiles exist (paid-directory group). | BL5: Not checked - ChatGPT/Perplexity/Gemini could not be queried from this session and the web-search budget was exhausted before the two money-question checks ('emergency tree removal near Kennesaw, GA', 'best tree service Kennesaw GA') ran. Schema check done: LocalBusiness + 5 Service entries in JSON-LD on every page, NO FAQPage schema and no FAQ content on home/tree-removal pages; robots.txt allows all crawlers. D4 scored 0 / NO EVIDENCE; run the spot-check before promoting to SEND TODAY. | BM5: PASS — Chain/franchise: no (independent GA Domestic Profit Corporation #0651574, Active/Compliance, 1 location, no franchise language; not Davey/Bartlett/SavATree/Monster). Website: own domain live, HTTP 200, © 2026, SSL. Live US business: Kennesaw GA address on site/BBB/SOS, BBB accredited since 2021, review on site 'a month ago', Oct 2026 promo active. Inbound channel: phone in header + contact form. Category: tree service (not competitor/non-buyer). Already automated: no AI receptionist, answering service or GEO vendor in page source; FAQPage schema absent. E4L world: 0 hits in suppression.csv and seen.csv for 'appalachian', 'appalachiantreeservice', 'strache'; GHL sub-account dedupe not run here. No 'no solicitation' notice found. | BN5: D1 Decision-maker reach: 14/20 — Full name + role from BBB ('Ryan Strache, President/Owner', https://www.bbb.org/us/ga/kennesaw/profile/tree-service/appalachian-tree-service-of-atlanta-inc-0443-27222938) corroborated by GA SOS data on OpenCorporates (registered agent 'Ryan Strache', https://opencorporates.com/companies/us_ga/0651574); personal-pattern email ryan@appalachiantreeservice.com published on the site header/footer/contact and in LocalBusiness JSON-LD (https://www.appalachiantreeservice.com/contact/), MX present; NO secondary channel (no LinkedIn, no owner social, no second phone) so not 20. | D2 Phone/after-hours gap: 15/15 — Phone-first (tel: in header, hero CTA 'Call for Free Estimate (404) 409-9926'); hours 'Monday–Friday: 9:00 AM–5:00 PM', 'Sat-Sun: Closed' (site + Nextdoor) while the site advertises 'Storm-Damage Tree Service' with the quoted gap 'during listed inquiry hours; no nighttime dispatch' and 'We review requests during our stated operating hours'; no 24/7, answering-service or AI-receptionist mention in page source. | D3 Lead-response leak: 5/15 — Exactly 1 signal type: (5) booking/contact friction verified in page source (no scheduler/chat/text vendor scripts; form has no response-time promise). Checked and null/inaccessible: Nextdoor (praise for response), site carousel (1 positive review), BBB (8 reviews, text not rendered), Yelp/Angi/HomeAdvisor/Indeed (403), /careers (404); GBP reply rate unknown. | D4 AI search gap: 0/10 NO EVIDENCE — no AI platform could be queried this turn; schema check only (LocalBusiness/Service present, no FAQPage). | D5 ICP fit/ability to pay: 15/15 — (a) independent GA Domestic Profit Corp, 1 location, named owner; (b) tree service passes the need test (niche-playbook fit 4/5, $500–$3k removals, storm cleanups $9k+); (c) proxies: since 2006 (site, BBB 2006-06-30, domain 2006-02-05), 100+ reviews (136 per site badge), 24-city service area, per-ticket value >= $1,000 by niche reference + Affirm financing in setup = 3+. | D6 Buying signals: 11/15 — Trigger within 60 days (Oct 1–31 promo on homepage; seasonal window with business-specific advertising) plus site relaunch 88 days ago and partner page 31 days ago; spend checklist: (a) Google Ads not checked (search budget), (b) LSA not checked, (c) Meta Ad Library 403, (d) no agency/pixel/call-tracking in source, (e) HomeAdvisor/Angi/Nextdoor/Yelp listings present. No (a)/(b)/(c) confirmed so not 15. | D7 Owner attitude/stack: 10/10 — Positives: (b) modern site © 2026 relaunched Jul 2026; (c) tech adoption (JSON-LD schema, AI-built site, digital payments, financing in setup); (e) growth posture (24 service-area pages, blog, promo, referral-partner pages). Negatives: none found. No incumbent agency/vertical bundle; greenfield. | TOTAL 70/100 = QUALIFIED. Status: TRUSTED (6 of 7 dimensions with evidence; D1 positive; D2 direct quotes; D5 cited) but NOT eligible for SEND TODAY until the D4 spot-check runs on at least one platform and GHL dedupe (ghl-contacts.js) is confirmed. | BO5: https://www.appalachiantreeservice.com/, https://www.appalachiantreeservice.com/contact/, https://www.bbb.org/us/ga/kennesaw/profile/tree-service/appalachian-tree-service-of-atlanta-inc-0443-27222938, https://opencorporates.com/companies/us_ga/0651574, https://www.appalachiantreeservice.com/about/, https://www.appalachiantreeservice.com/financing, https://www.appalachiantreeservice.com/tree-removal, https://www.appalachiantreeservice.com/sitemap.xml, https://www.appalachiantreeservice.com/hvac, https://www.appalachiantreeservice.com/contact?promotion=spooky-trees-october-2026, https://nextdoor.com/pages/appalachian-tree-service-kennesaw-ga-1/, https://www.appalachiantreeservice.com/gallery, https://www.appalachiantreeservice.com/robots.txt, https://rdap.org/domain/appalachiantreeservice.com, https://dns.google/resolve?name=appalachiantreeservice.com&type=MX, https://g.page/appalachian-tree-service, https://www.yelp.com/biz/appalachian-tree-service-kennesaw-2, https://www.angi.com/companylist/us/ga/kennesaw/appalachian-tree-service-of-atlanta-reviews-2847650.htm, https://www.homeadvisor.com/rated.AppalachianTreeService.67089025.html, https://www.facebook.com/AppalachianTree, https://www.instagram.com/appalachian_tree_service/, https://x.com/appalachian_of | BP5: Medium | BQ5: Title detail: President/Owner (BBB Business Management: 'Ryan Strache, President/Owner'); also Registered Agent of the GA corporation (OpenCorporates #0651574). 1) Band = QUALIFIED (70, TRUSTED on 6/7 dimensions) but held out of SEND TODAY only because the D4 AI spot-check could not run this turn (web-search budget exhausted; AI platforms not reachable) — one Perplexity/ChatGPT pass on 'emergency tree removal near Kennesaw, GA' promotes it. 2) GHL 'E4L Services' dedupe (ghl-contacts.js by domain/phone/name+city) was NOT run from this subagent; suppression.csv and seen.csv are clean (0 hits for name, domain, Strache). 3) Email route: ryan@appalachiantreeservice.com is Confirmed (on the business's own site + JSON-LD, Google Workspace MX); send from Sebastian plain-text, Sam calls within 48 h. 4) Google/Yelp/Angi/HomeAdvisor reviews and Facebook/Instagram/X could not be opened (403/login walls), so review-reply behavior and social cadence are unknown — Rozel may want a quick manual look at the GBP before send. 5) The site is built on Manus (AI website builder) — he has already used an AI tool, so 'AI' is not a scary word, but lead with the 9 PM storm call, not the tech. 6) Do not say he misses calls (Nextdoor praises his response speed); frame as after-hours and storm-surge coverage. 7) OpenCorporates lists the registered agent at a non-business address — not recorded, do not use. 8) Demo scenario for Abdullah: tree on the house after a storm at night; AI collects name, number, address, what fell, offers the free estimate and books the next-morning assessment; no nighttime dispatch promised. 9) Referral partners on his site (roofing, HVAC, landscaping, stump grinding, arborist) are a possible referral angle later — the HVAC partner (Top Tech Mechanical) advertises 24-hour emergency service, a natural contrast he will recognize.
